{"id":"Hume.THN.2.1.7","documentCount":1,"importedDocumentCount":1,"wordCount":1193,"lemmaWordCount":1193,"numberWordCount":0,"nameWordCount":0,"foreignWordCount":0,"citationWordCount":0,"marginCommentWordCount":0,"lemmas":[{"label":"humility","frequency":9,"documentFrequency":1,"idf":2.588505050452427,"absoluteTfIdf":23.296545454071843,"relativeTfIdf":0.019527699458568186},{"label":"the","frequency":65,"documentFrequency":1,"idf":0.35290277801730885,"absoluteTfIdf":22.938680571125076,"relativeTfIdf":0.019227728894488746},{"label":"and","frequency":58,"documentFrequency":1,"idf":0.3559193715567345,"absoluteTfIdf":20.6433235502906,"relativeTfIdf":0.01730370792145063},{"label":"of","frequency":57,"documentFrequency":1,"idf":0.34989525695335355,"absoluteTfIdf":19.944029646341153,"relativeTfIdf":0.016717543710260813},{"label":"uneasiness","frequency":8,"documentFrequency":1,"idf":2.256065077359153,"absoluteTfIdf":18.048520618873223,"relativeTfIdf":0.015128684508695074},{"label":"be","frequency":49,"documentFrequency":1,"idf":0.3619799961684256,"absoluteTfIdf":17.737019812252854,"relativeTfIdf":0.014867577378250505},{"label":"pride","frequency":9,"documentFrequency":1,"idf":1.8472386215482837,"absoluteTfIdf":16.625147593934553,"relativeTfIdf":0.013935580548142961},{"label":"vice","frequency":11,"documentFrequency":1,"idf":1.378914253822268,"absoluteTfIdf":15.168056792044949,"relativeTfIdf":0.012714213572543962},{"label":"hypothesis","frequency":7,"documentFrequency":1,"idf":2.089010992695987,"absoluteTfIdf":14.623076948871908,"relativeTfIdf":0.012257398951275698},{"label":"morality","frequency":6,"documentFrequency":1,"idf":2.178356093031837,"absoluteTfIdf":13.07013655819102,"relativeTfIdf":0.010955688648944695},{"label":"to","frequency":37,"documentFrequency":1,"idf":0.35290277801730885,"absoluteTfIdf":13.057402786640427,"relativeTfIdf":0.010945014909170518},{"label":"we","frequency":32,"documentFrequency":1,"idf":0.3865966238037816,"absoluteTfIdf":12.371091961721012,"relativeTfIdf":0.01036973341301007},{"label":"virtue","frequency":13,"documentFrequency":1,"idf":0.9162907318741551,"absoluteTfIdf":11.911779514364017,"relativeTfIdf":0.009984727170464388},{"label":"a","frequency":31,"documentFrequency":1,"idf":0.35743108764205644,"absoluteTfIdf":11.080363716903749,"relativeTfIdf":0.009287815353649413},{"label":"pleasure","frequency":12,"documentFrequency":1,"idf":0.8157034949689864,"absoluteTfIdf":9.788441939627837,"relativeTfIdf":0.008204896847969687},{"label":"that","frequency":26,"documentFrequency":1,"idf":0.3696077982173117,"absoluteTfIdf":9.609802753650104,"relativeTfIdf":0.008055157379421713},{"label":"or","frequency":22,"documentFrequency":1,"idf":0.3788386329928422,"absoluteTfIdf":8.334449925842529,"relativeTfIdf":0.006986127347730534},{"label":"from","frequency":21,"documentFrequency":1,"idf":0.38971675114002524,"absoluteTfIdf":8.18405177394053,"relativeTfIdf":0.006860060162565407},{"label":"pain","frequency":7,"documentFrequency":1,"idf":1.1608254731696823,"absoluteTfIdf":8.125778312187776,"relativeTfIdf":0.006811214008539628},{"label":"wit","frequency":5,"documentFrequency":1,"idf":1.5936895554659611,"absoluteTfIdf":7.968447777329805,"relativeTfIdf":0.00667933594076262},{"label":"system","frequency":6,"documentFrequency":1,"idf":1.3177954387662225,"absoluteTfIdf":7.906772632597335,"relativeTfIdf":0.006627638417935738},{"label":"impression","frequency":5,"documentFrequency":1,"idf":1.4350845252893227,"absoluteTfIdf":7.175422626446614,"relativeTfIdf":0.006014604045638402},{"label":"delight","frequency":4,"documentFrequency":1,"idf":1.7574347266869803,"absoluteTfIdf":7.029738906747921,"relativeTfIdf":0.005892488605823907},{"label":"it","frequency":19,"documentFrequency":1,"idf":0.3696077982173117,"absoluteTfIdf":7.022548166128923,"relativeTfIdf":0.005886461161885098},{"label":"this","frequency":19,"documentFrequency":1,"idf":0.3665496918584909,"absoluteTfIdf":6.964444145311327,"relativeTfIdf":0.005837757037142772},{"label":"dis-approbation","frequency":1,"documentFrequency":1,"idf":6.851184927493743,"absoluteTfIdf":6.851184927493743,"relativeTfIdf":0.005742820559508586},{"label":"essence","frequency":3,"documentFrequency":1,"idf":2.226212114209472,"absoluteTfIdf":6.678636342628415,"relativeTfIdf":0.00559818637269775},{"label":"which","frequency":18,"documentFrequency":1,"idf":0.3696077982173117,"absoluteTfIdf":6.652940367911611,"relativeTfIdf":0.005576647416522725},{"label":"character","frequency":6,"documentFrequency":1,"idf":1.0704414117014134,"absoluteTfIdf":6.422648470208481,"relativeTfIdf":0.005383611458682716},{"label":"moral","frequency":5,"documentFrequency":1,"idf":1.2199731456723772,"absoluteTfIdf":6.099865728361886,"relativeTfIdf":0.005113047551015831},{"label":"in","frequency":17,"documentFrequency":1,"idf":0.35743108764205644,"absoluteTfIdf":6.076328489914959,"relativeTfIdf":0.005093318097162581},{"label":"they","frequency":15,"documentFrequency":1,"idf":0.37421256460405994,"absoluteTfIdf":5.6131884690608995,"relativeTfIdf":0.004705103494602597},{"label":"denomination","frequency":2,"documentFrequency":1,"idf":2.7907419169473235,"absoluteTfIdf":5.581483833894647,"relativeTfIdf":0.004678527941236083},{"label":"excite","frequency":4,"documentFrequency":1,"idf":1.3417965908657654,"absoluteTfIdf":5.367186363463062,"relativeTfIdf":0.004498898879684042},{"label":"primary","frequency":2,"documentFrequency":1,"idf":2.661530185467317,"absoluteTfIdf":5.323060370934634,"relativeTfIdf":0.004461911459291395},{"label":"cause","frequency":8,"documentFrequency":1,"idf":0.664976303593249,"absoluteTfIdf":5.319810428745992,"relativeTfIdf":0.004459187283106448},{"label":"false","frequency":4,"documentFrequency":1,"idf":1.302108842598523,"absoluteTfIdf":5.208435370394092,"relativeTfIdf":0.0043658301512104715},{"label":"arise","frequency":6,"documentFrequency":1,"idf":0.8301615781442164,"absoluteTfIdf":4.980969468865299,"relativeTfIdf":0.00417516300826932},{"label":"passion","frequency":6,"documentFrequency":1,"idf":0.806179613457731,"absoluteTfIdf":4.837077680746386,"relativeTfIdf":0.004054549606660843},{"label":"proof","frequency":4,"documentFrequency":1,"idf":1.1986957472250923,"absoluteTfIdf":4.794782988900369,"relativeTfIdf":0.004019097224560243},{"label":"i","frequency":10,"documentFrequency":1,"idf":0.4592678141011407,"absoluteTfIdf":4.592678141011407,"relativeTfIdf":0.003849688299255161},{"label":"check'd","frequency":1,"documentFrequency":1,"idf":4.548599834499697,"absoluteTfIdf":4.548599834499697,"relativeTfIdf":0.0038127408503769466},{"label":"inseparable","frequency":2,"documentFrequency":1,"idf":2.2460147415056513,"absoluteTfIdf":4.492029483011303,"relativeTfIdf":0.003765322282490614},{"label":"but","frequency":12,"documentFrequency":1,"idf":0.37421256460405994,"absoluteTfIdf":4.490550775248719,"relativeTfIdf":0.003764082795682078},{"label":"ethicks","frequency":1,"documentFrequency":1,"idf":4.453289654695372,"absoluteTfIdf":4.453289654695372,"relativeTfIdf":0.003732849668646582},{"label":"double","frequency":2,"documentFrequency":1,"idf":2.0720614343822135,"absoluteTfIdf":4.144122868764427,"relativeTfIdf":0.0034736989679500646},{"label":"defender","frequency":1,"documentFrequency":1,"idf":4.0785962052539615,"absoluteTfIdf":4.0785962052539615,"relativeTfIdf":0.003418773013624444},{"label":"produce","frequency":5,"documentFrequency":1,"idf":0.7967455812243723,"absoluteTfIdf":3.9837279061218616,"relativeTfIdf":0.0033392522264223483},{"label":"distinction","frequency":3,"documentFrequency":1,"idf":1.3060074830141803,"absoluteTfIdf":3.918022449042541,"relativeTfIdf":0.003284176403220906},{"label":"latter","frequency":4,"documentFrequency":1,"idf":0.9790671380183269,"absoluteTfIdf":3.9162685520733076,"relativeTfIdf":0.0032827062464990007},{"label":"other","frequency":10,"documentFrequency":1,"idf":0.3850402032561233,"absoluteTfIdf":3.850402032561233,"relativeTfIdf":0.0032274954170672535},{"label":"baseness","frequency":1,"documentFrequency":1,"idf":3.760142474135427,"absoluteTfIdf":3.760142474135427,"relativeTfIdf":0.0031518377821755468},{"label":"have","frequency":10,"documentFrequency":1,"idf":0.3680775760365441,"absoluteTfIdf":3.6807757603654414,"relativeTfIdf":0.0030853107798536807},{"label":"possest","frequency":1,"documentFrequency":1,"idf":3.6731310971457973,"absoluteTfIdf":3.6731310971457973,"relativeTfIdf":0.0030789028475656306},{"label":"generous","frequency":2,"documentFrequency":1,"idf":1.8207470061013074,"absoluteTfIdf":3.6414940122026147,"relativeTfIdf":0.0030523839163475396},{"label":"demerit","frequency":1,"documentFrequency":1,"idf":3.632309102625542,"absoluteTfIdf":3.632309102625542,"relativeTfIdf":0.0030446849141873783},{"label":"nature","frequency":7,"documentFrequency":1,"idf":0.5090635087725914,"absoluteTfIdf":3.56344456140814,"relativeTfIdf":0.0029869610741057335},{"label":"self-evident","frequency":1,"documentFrequency":1,"idf":3.5553480614894135,"absoluteTfIdf":3.5553480614894135,"relativeTfIdf":0.002980174401919039},{"label":"sensation","frequency":2,"documentFrequency":1,"idf":1.76978056250928,"absoluteTfIdf":3.53956112501856,"relativeTfIdf":0.0029669414291857168},{"label":"former","frequency":4,"documentFrequency":1,"idf":0.882477367508377,"absoluteTfIdf":3.529909470033508,"relativeTfIdf":0.002958851190304701},{"label":"strenuously","frequency":1,"documentFrequency":1,"idf":3.518980417318539,"absoluteTfIdf":3.518980417318539,"relativeTfIdf":0.0029496902073080796},{"label":"unquestionable","frequency":1,"documentFrequency":1,"idf":3.4171977230085964,"absoluteTfIdf":3.4171977230085964,"relativeTfIdf":0.0028643736152628636},{"label":"by","frequency":9,"documentFrequency":1,"idf":0.3696077982173117,"absoluteTfIdf":3.3264701839558053,"relativeTfIdf":0.0027883237082613624},{"label":"villainy","frequency":1,"documentFrequency":1,"idf":3.3248244028775815,"absoluteTfIdf":3.3248244028775815,"relativeTfIdf":0.0027869441767624323},{"label":"taste","frequency":2,"documentFrequency":1,"idf":1.6582280766035324,"absoluteTfIdf":3.316456153207065,"relativeTfIdf":0.0027799297176924267},{"label":"allow","frequency":4,"documentFrequency":1,"idf":0.82773733453271,"absoluteTfIdf":3.31094933813084,"relativeTfIdf":0.00277531377881881},{"label":"self-interest","frequency":1,"documentFrequency":1,"idf":3.2676659890376327,"absoluteTfIdf":3.2676659890376327,"relativeTfIdf":0.002739032681506817},{"label":"education","frequency":2,"documentFrequency":1,"idf":1.6308291024154178,"absoluteTfIdf":3.2616582048308356,"relativeTfIdf":0.0027339968188020416},{"label":"cowardice","frequency":1,"documentFrequency":1,"idf":3.2402670148495183,"absoluteTfIdf":3.2402670148495183,"relativeTfIdf":0.0027160662320616247},{"label":"undeniable","frequency":1,"documentFrequency":1,"idf":3.2402670148495183,"absoluteTfIdf":3.2402670148495183,"relativeTfIdf":0.0027160662320616247},{"label":"invincible","frequency":1,"documentFrequency":1,"idf":3.213598767767357,"absoluteTfIdf":3.213598767767357,"relativeTfIdf":0.002693712294859478},{"label":"fable","frequency":1,"documentFrequency":1,"idf":3.1623054733798064,"absoluteTfIdf":3.1623054733798064,"relativeTfIdf":0.0026507170774348753},{"label":"liberality","frequency":1,"documentFrequency":1,"idf":3.1623054733798064,"absoluteTfIdf":3.1623054733798064,"relativeTfIdf":0.0026507170774348753},{"label":"pulpit","frequency":1,"documentFrequency":1,"idf":3.137612860789435,"absoluteTfIdf":3.137612860789435,"relativeTfIdf":0.0026300191624387555},{"label":"quality","frequency":3,"documentFrequency":1,"idf":1.043042437513299,"absoluteTfIdf":3.1291273125398966,"relativeTfIdf":0.002622906381005781},{"label":"poem","frequency":1,"documentFrequency":1,"idf":3.1135153092103742,"absoluteTfIdf":3.1135153092103742,"relativeTfIdf":0.002609820041249266},{"label":"grant","frequency":2,"documentFrequency":1,"idf":1.547880019434667,"absoluteTfIdf":3.095760038869334,"relativeTfIdf":0.00259493716585862},{"label":"prejudice","frequency":2,"documentFrequency":1,"idf":1.547880019434667,"absoluteTfIdf":3.095760038869334,"relativeTfIdf":0.00259493716585862},{"label":"mortification","frequency":1,"documentFrequency":1,"idf":3.0899848118001803,"absoluteTfIdf":3.0899848118001803,"relativeTfIdf":0.0025900962378878293},{"label":"present","frequency":5,"documentFrequency":1,"idf":0.6070180268300066,"absoluteTfIdf":3.035090134150033,"relativeTfIdf":0.002544082258298435},{"label":"on","frequency":7,"documentFrequency":1,"idf":0.42793796396022304,"absoluteTfIdf":2.995565747721561,"relativeTfIdf":0.002510952009825282},{"label":"mortify","frequency":1,"documentFrequency":1,"idf":2.9391619220655967,"absoluteTfIdf":2.9391619220655967,"relativeTfIdf":0.0024636730277163427},{"label":"either","frequency":5,"documentFrequency":1,"idf":0.5783079209475752,"absoluteTfIdf":2.891539604737876,"relativeTfIdf":0.002423754907575755},{"label":"merit","frequency":2,"documentFrequency":1,"idf":1.4262349100123402,"absoluteTfIdf":2.8524698200246803,"relativeTfIdf":0.0023910057167013245},{"label":"disapprove","frequency":1,"documentFrequency":1,"idf":2.843851742261272,"absoluteTfIdf":2.843851742261272,"relativeTfIdf":0.002383781845985978},{"label":"opposite","frequency":2,"documentFrequency":1,"idf":1.4131056185705473,"absoluteTfIdf":2.8262112371410946,"relativeTfIdf":0.002368995169439308},{"label":"remorse","frequency":1,"documentFrequency":1,"idf":2.8081336596591924,"absoluteTfIdf":2.8081336596591924,"relativeTfIdf":0.0023538421288006642},{"label":"principally","frequency":1,"documentFrequency":1,"idf":2.7736474835880234,"absoluteTfIdf":2.7736474835880234,"relativeTfIdf":0.0023249350239631377},{"label":"upon","frequency":6,"documentFrequency":1,"idf":0.460944260428393,"absoluteTfIdf":2.7656655625703577,"relativeTfIdf":0.0023182443944428817},{"label":"any","frequency":7,"documentFrequency":1,"idf":0.3850402032561233,"absoluteTfIdf":2.6952814227928634,"relativeTfIdf":0.0022592467919470773},{"label":"satisfaction","frequency":2,"documentFrequency":1,"idf":1.34585339156138,"absoluteTfIdf":2.69170678312276,"relativeTfIdf":0.0022562504468757417},{"label":"maintain","frequency":2,"documentFrequency":1,"idf":1.3377561813287606,"absoluteTfIdf":2.6755123626575212,"relativeTfIdf":0.002242675911699515},{"label":"with","frequency":7,"documentFrequency":1,"idf":0.3819346106979702,"absoluteTfIdf":2.6735422748857913,"relativeTfIdf":0.002241024538881636},{"label":"accomplishment","frequency":1,"documentFrequency":1,"idf":2.631677222317636,"absoluteTfIdf":2.631677222317636,"relativeTfIdf":0.0022059322902913967},{"label":"quickly","frequency":1,"documentFrequency":1,"idf":2.6170784228964834,"absoluteTfIdf":2.6170784228964834,"relativeTfIdf":0.0021936952413214444},{"label":"attendant","frequency":1,"documentFrequency":1,"idf":2.6026896854443837,"absoluteTfIdf":2.6026896854443837,"relativeTfIdf":0.002181634271118511},{"label":"original","frequency":2,"documentFrequency":1,"idf":1.2828404237326458,"absoluteTfIdf":2.5656808474652917,"relativeTfIdf":0.0021506126131310074},{"label":"agree","frequency":2,"documentFrequency":1,"idf":1.2790308953159784,"absoluteTfIdf":2.5580617906319567,"relativeTfIdf":0.002144226144704071},{"label":"fruitless","frequency":1,"documentFrequency":1,"idf":2.547119834289573,"absoluteTfIdf":2.547119834289573,"relativeTfIdf":0.002135054345590589},{"label":"limitation","frequency":1,"documentFrequency":1,"idf":2.547119834289573,"absoluteTfIdf":2.547119834289573,"relativeTfIdf":0.002135054345590589},{"label":"solidity","frequency":1,"documentFrequency":1,"idf":2.547119834289573,"absoluteTfIdf":2.547119834289573,"relativeTfIdf":0.002135054345590589},{"label":"avarice","frequency":1,"documentFrequency":1,"idf":2.533696813957432,"absoluteTfIdf":2.533696813957432,"relativeTfIdf":0.002123802861657529},{"label":"treachery","frequency":1,"documentFrequency":1,"idf":2.533696813957432,"absoluteTfIdf":2.533696813957432,"relativeTfIdf":0.002123802861657529},{"label":"derive","frequency":2,"documentFrequency":1,"idf":1.2601979469828861,"absoluteTfIdf":2.5203958939657722,"relativeTfIdf":0.0021126537250341763},{"label":"rigid","frequency":1,"documentFrequency":1,"idf":2.507379505640059,"absoluteTfIdf":2.507379505640059,"relativeTfIdf":0.0021017430893881467},{"label":"style","frequency":1,"documentFrequency":1,"idf":2.507379505640059,"absoluteTfIdf":2.507379505640059,"relativeTfIdf":0.0021017430893881467},{"label":"very","frequency":5,"documentFrequency":1,"idf":0.49334266098564317,"absoluteTfIdf":2.466713304928216,"relativeTfIdf":0.00206765574595827},{"label":"consequently","frequency":2,"documentFrequency":1,"idf":1.2057380298505052,"absoluteTfIdf":2.4114760597010103,"relativeTfIdf":0.00202135461835793},{"label":"must","frequency":5,"documentFrequency":1,"idf":0.4795730802618863,"absoluteTfIdf":2.3978654013094314,"relativeTfIdf":0.0020099458518939074},{"label":"unavoidable","frequency":1,"documentFrequency":1,"idf":2.340325420976893,"absoluteTfIdf":2.340325420976893,"relativeTfIdf":0.0019617145188406478},{"label":"disappointment","frequency":1,"documentFrequency":1,"idf":2.3293963504447026,"absoluteTfIdf":2.3293963504447026,"relativeTfIdf":0.0019525535209092228},{"label":"may","frequency":6,"documentFrequency":1,"idf":0.38815547057307265,"absoluteTfIdf":2.3289328234384357,"relativeTfIdf":0.0019521649819266018},{"label":"school","frequency":1,"documentFrequency":1,"idf":2.307890145223739,"absoluteTfIdf":2.307890145223739,"relativeTfIdf":0.0019345265257533436},{"label":"talent","frequency":1,"documentFrequency":1,"idf":2.307890145223739,"absoluteTfIdf":2.307890145223739,"relativeTfIdf":0.0019345265257533436},{"label":"rights","frequency":1,"documentFrequency":1,"idf":2.2868367360259065,"absoluteTfIdf":2.2868367360259065,"relativeTfIdf":0.0019168790746235595},{"label":"for","frequency":6,"documentFrequency":1,"idf":0.3803854237111409,"absoluteTfIdf":2.2823125422668458,"relativeTfIdf":0.0019130867915061573},{"label":"not","frequency":6,"documentFrequency":1,"idf":0.3788386329928422,"absoluteTfIdf":2.2730317979570533,"relativeTfIdf":0.0019053074584719641},{"label":"charm","frequency":1,"documentFrequency":1,"idf":2.2460147415056513,"absoluteTfIdf":2.2460147415056513,"relativeTfIdf":0.001882661141245307},{"label":"receive","frequency":3,"documentFrequency":1,"idf":0.7486263328801739,"absoluteTfIdf":2.2458789986405217,"relativeTfIdf":0.001882547358458107},{"label":"whether","frequency":3,"documentFrequency":1,"idf":0.7486263328801739,"absoluteTfIdf":2.2458789986405217,"relativeTfIdf":0.001882547358458107},{"label":"examine","frequency":2,"documentFrequency":1,"idf":1.1210851445201684,"absoluteTfIdf":2.2421702890403368,"relativeTfIdf":0.0018794386328921516},{"label":"relation","frequency":2,"documentFrequency":1,"idf":1.114612630014551,"absoluteTfIdf":2.229225260029102,"relativeTfIdf":0.0018685878122624493},{"label":"as","frequency":6,"documentFrequency":1,"idf":0.3696077982173117,"absoluteTfIdf":2.2176467893038705,"relativeTfIdf":0.0018588824721742416},{"label":"tell","frequency":2,"documentFrequency":1,"idf":1.1049817369535895,"absoluteTfIdf":2.209963473907179,"relativeTfIdf":0.0018524421407436539},{"label":"exalt","frequency":1,"documentFrequency":1,"idf":2.1972245773362196,"absoluteTfIdf":2.1972245773362196,"relativeTfIdf":0.001841764105059698},{"label":"survey","frequency":1,"documentFrequency":1,"idf":2.1972245773362196,"absoluteTfIdf":2.1972245773362196,"relativeTfIdf":0.001841764105059698},{"label":"attend","frequency":2,"documentFrequency":1,"idf":1.0954427139068306,"absoluteTfIdf":2.190885427813661,"relativeTfIdf":0.0018364504843366815},{"label":"decide","frequency":1,"documentFrequency":1,"idf":2.169053700369523,"absoluteTfIdf":2.169053700369523,"relativeTfIdf":0.0018181506289769683},{"label":"vicious","frequency":1,"documentFrequency":1,"idf":2.169053700369523,"absoluteTfIdf":2.169053700369523,"relativeTfIdf":0.0018181506289769683},{"label":"attack","frequency":1,"documentFrequency":1,"idf":2.159837045264599,"absoluteTfIdf":2.159837045264599,"relativeTfIdf":0.0018104250169862525},{"label":"contemplation","frequency":1,"documentFrequency":1,"idf":2.1507045617013265,"absoluteTfIdf":2.1507045617013265,"relativeTfIdf":0.0018027699595149426},{"label":"cruelty","frequency":1,"documentFrequency":1,"idf":2.1416547261814087,"absoluteTfIdf":2.1416547261814087,"relativeTfIdf":0.001795184179531776},{"label":"esteem","frequency":2,"documentFrequency":1,"idf":1.0704414117014134,"absoluteTfIdf":2.1408828234028268,"relativeTfIdf":0.0017945371528942386},{"label":"curiosity","frequency":1,"documentFrequency":1,"idf":2.132686056198648,"absoluteTfIdf":2.132686056198648,"relativeTfIdf":0.0017876664343660085},{"label":"evident","frequency":2,"documentFrequency":1,"idf":1.0642875461270351,"absoluteTfIdf":2.1285750922540703,"relativeTfIdf":0.0017842205299698829},{"label":"feel","frequency":2,"documentFrequency":1,"idf":1.052092273033217,"absoluteTfIdf":2.104184546066434,"relativeTfIdf":0.0017637758139701877},{"label":"purpose","frequency":2,"documentFrequency":1,"idf":1.052092273033217,"absoluteTfIdf":2.104184546066434,"relativeTfIdf":0.0017637758139701877},{"label":"true","frequency":3,"documentFrequency":1,"idf":0.7005821590474633,"absoluteTfIdf":2.10174647714239,"relativeTfIdf":0.001761732168602171},{"label":"flatter","frequency":1,"documentFrequency":1,"idf":2.089010992695987,"absoluteTfIdf":2.089010992695987,"relativeTfIdf":0.0017510569930393855},{"label":"standard","frequency":1,"documentFrequency":1,"idf":2.089010992695987,"absoluteTfIdf":2.089010992695987,"relativeTfIdf":0.0017510569930393855},{"label":"still","frequency":3,"documentFrequency":1,"idf":0.6942059419081874,"absoluteTfIdf":2.0826178257245624,"relativeTfIdf":0.0017456980936500941},{"label":"displease","frequency":1,"documentFrequency":1,"idf":2.063693184711697,"absoluteTfIdf":2.063693184711697,"relativeTfIdf":0.0017298350249050267},{"label":"reserve","frequency":1,"documentFrequency":1,"idf":2.0228711901914416,"absoluteTfIdf":2.0228711901914416,"relativeTfIdf":0.0016956170915267742},{"label":"can","frequency":5,"documentFrequency":1,"idf":0.3991359730565169,"absoluteTfIdf":1.9956798652825845,"relativeTfIdf":0.0016728246984766006},{"label":"sensible","frequency":2,"documentFrequency":1,"idf":0.9961130052913156,"absoluteTfIdf":1.9922260105826313,"relativeTfIdf":0.0016699295981413506},{"label":"forego","frequency":1,"documentFrequency":1,"idf":1.9836504770381604,"absoluteTfIdf":1.9836504770381604,"relativeTfIdf":0.0016627413889674439},{"label":"every","frequency":4,"documentFrequency":1,"idf":0.49334266098564317,"absoluteTfIdf":1.9733706439425727,"relativeTfIdf":0.0016541245967666158},{"label":"controversy","frequency":1,"documentFrequency":1,"idf":1.960835799271989,"absoluteTfIdf":1.960835799271989,"relativeTfIdf":0.001643617602072078},{"label":"origin","frequency":1,"documentFrequency":1,"idf":1.9533451275428313,"absoluteTfIdf":1.9533451275428313,"relativeTfIdf":0.0016373387489881234},{"label":"vanity","frequency":1,"documentFrequency":1,"idf":1.9533451275428313,"absoluteTfIdf":1.9533451275428313,"relativeTfIdf":0.0016373387489881234},{"label":"reconcile","frequency":1,"documentFrequency":1,"idf":1.9459101490553132,"absoluteTfIdf":1.9459101490553132,"relativeTfIdf":0.0016311065792584353},{"label":"all","frequency":5,"documentFrequency":1,"idf":0.38815547057307265,"absoluteTfIdf":1.9407773528653633,"relativeTfIdf":0.0016268041516055015},{"label":"scruple","frequency":1,"documentFrequency":1,"idf":1.9385300417576907,"absoluteTfIdf":1.9385300417576907,"relativeTfIdf":0.001624920403820361},{"label":"constitute","frequency":1,"documentFrequency":1,"idf":1.9312040016656178,"absoluteTfIdf":1.9312040016656178,"relativeTfIdf":0.0016187795487557569},{"label":"endeavour","frequency":2,"documentFrequency":1,"idf":0.965080896043587,"absoluteTfIdf":1.930161792087174,"relativeTfIdf":0.0016179059447503554},{"label":"essential","frequency":1,"documentFrequency":1,"idf":1.9095425048844383,"absoluteTfIdf":1.9095425048844383,"relativeTfIdf":0.0016006223846474757},{"label":"examination","frequency":1,"documentFrequency":1,"idf":1.9095425048844383,"absoluteTfIdf":1.9095425048844383,"relativeTfIdf":0.0016006223846474757},{"label":"injustice","frequency":1,"documentFrequency":1,"idf":1.9024250371155744,"absoluteTfIdf":1.9024250371155744,"relativeTfIdf":0.00159465635969453},{"label":"find","frequency":4,"documentFrequency":1,"idf":0.4744579795951159,"absoluteTfIdf":1.8978319183804635,"relativeTfIdf":0.0015908063020791815},{"label":"obligation","frequency":1,"documentFrequency":1,"idf":1.8883402972338355,"absoluteTfIdf":1.8883402972338355,"relativeTfIdf":0.0015828502072370793},{"label":"observe","frequency":3,"documentFrequency":1,"idf":0.626626498218383,"absoluteTfIdf":1.8798794946551491,"relativeTfIdf":0.0015757581681937545},{"label":"only","frequency":4,"documentFrequency":1,"idf":0.4659905284960173,"absoluteTfIdf":1.8639621139840692,"relativeTfIdf":0.00156241585413585},{"label":"many","frequency":5,"documentFrequency":1,"idf":0.3726752852851735,"absoluteTfIdf":1.8633764264258676,"relativeTfIdf":0.0015619249173728983},{"label":"surprise","frequency":1,"documentFrequency":1,"idf":1.8607523407150066,"absoluteTfIdf":1.8607523407150066,"relativeTfIdf":0.0015597253484618664},{"label":"able","frequency":2,"documentFrequency":1,"idf":0.9296065078499273,"absoluteTfIdf":1.8592130156998545,"relativeTfIdf":0.0015584350508800122},{"label":"real","frequency":2,"documentFrequency":1,"idf":0.9296065078499273,"absoluteTfIdf":1.8592130156998545,"relativeTfIdf":0.0015584350508800122},{"label":"approbation","frequency":1,"documentFrequency":1,"idf":1.8539726537296277,"absoluteTfIdf":1.8539726537296277,"relativeTfIdf":0.0015540424591195538},{"label":"manner","frequency":3,"documentFrequency":1,"idf":0.6167742017753713,"absoluteTfIdf":1.850322605326114,"relativeTfIdf":0.001550982904715938},{"label":"trouble","frequency":1,"documentFrequency":1,"idf":1.8472386215482837,"absoluteTfIdf":1.8472386215482837,"relativeTfIdf":0.0015483978386825513},{"label":"let","frequency":2,"documentFrequency":1,"idf":0.9215957841038481,"absoluteTfIdf":1.8431915682076963,"relativeTfIdf":0.001545005505622545},{"label":"prove","frequency":2,"documentFrequency":1,"idf":0.9189397400457321,"absoluteTfIdf":1.8378794800914642,"relativeTfIdf":0.0015405527913591485},{"label":"blame","frequency":1,"documentFrequency":1,"idf":1.8273044066474664,"absoluteTfIdf":1.8273044066474664,"relativeTfIdf":0.0015316885219174069},{"label":"operate","frequency":1,"documentFrequency":1,"idf":1.8207470061013074,"absoluteTfIdf":1.8207470061013074,"relativeTfIdf":0.0015261919581737698},{"label":"ruin","frequency":1,"documentFrequency":1,"idf":1.807759810574496,"absoluteTfIdf":1.807759810574496,"relativeTfIdf":0.0015153057926022599},{"label":"courage","frequency":1,"documentFrequency":1,"idf":1.8013289202442055,"absoluteTfIdf":1.8013289202442055,"relativeTfIdf":0.0015099152726271632},{"label":"advantage","frequency":2,"documentFrequency":1,"idf":0.900542374906016,"absoluteTfIdf":1.801084749812032,"relativeTfIdf":0.0015097106033629772},{"label":"prospect","frequency":1,"documentFrequency":1,"idf":1.788589894466776,"absoluteTfIdf":1.788589894466776,"relativeTfIdf":0.0014992371286393763},{"label":"tendency","frequency":1,"documentFrequency":1,"idf":1.788589894466776,"absoluteTfIdf":1.788589894466776,"relativeTfIdf":0.0014992371286393763},{"label":"virtuous","frequency":1,"documentFrequency":1,"idf":1.7822807252735113,"absoluteTfIdf":1.7822807252735113,"relativeTfIdf":0.0014939486381169416},{"label":"habit","frequency":1,"documentFrequency":1,"idf":1.76978056250928,"absoluteTfIdf":1.76978056250928,"relativeTfIdf":0.0014834707145928584},{"label":"view","frequency":2,"documentFrequency":1,"idf":0.8773753156244816,"absoluteTfIdf":1.7547506312489631,"relativeTfIdf":0.0014708722810133808},{"label":"accustom","frequency":1,"documentFrequency":1,"idf":1.7452394535931621,"absoluteTfIdf":1.7452394535931621,"relativeTfIdf":0.0014628997934561293},{"label":"riches","frequency":1,"documentFrequency":1,"idf":1.7331911150769876,"absoluteTfIdf":1.7331911150769876,"relativeTfIdf":0.0014528005993939544},{"label":"approve","frequency":1,"documentFrequency":1,"idf":1.7095213709910828,"absoluteTfIdf":1.7095213709910828,"relativeTfIdf":0.0014329600762708155},{"label":"result","frequency":1,"documentFrequency":1,"idf":1.70369045068029,"absoluteTfIdf":1.70369045068029,"relativeTfIdf":0.0014280724649457586},{"label":"enquire","frequency":1,"documentFrequency":1,"idf":1.6978933329959638,"absoluteTfIdf":1.6978933329959638,"relativeTfIdf":0.0014232131877585615},{"label":"mind","frequency":3,"documentFrequency":1,"idf":0.5651868329848782,"absoluteTfIdf":1.6955604989546345,"relativeTfIdf":0.0014212577526861983},{"label":"foreign","frequency":1,"documentFrequency":1,"idf":1.6921296282792138,"absoluteTfIdf":1.6921296282792138,"relativeTfIdf":0.0014183819180881925},{"label":"consider","frequency":3,"documentFrequency":1,"idf":0.5614693565847456,"absoluteTfIdf":1.684408069754237,"relativeTfIdf":0.001411909530389134},{"label":"defend","frequency":1,"documentFrequency":1,"idf":1.6694013772016576,"absoluteTfIdf":1.6694013772016576,"relativeTfIdf":0.0013993305760282126},{"label":"regard","frequency":2,"documentFrequency":1,"idf":0.8325917129975081,"absoluteTfIdf":1.6651834259950162,"relativeTfIdf":0.0013957949924518157},{"label":"noble","frequency":1,"documentFrequency":1,"idf":1.6637991216529877,"absoluteTfIdf":1.6637991216529877,"relativeTfIdf":0.0013946346367585815},{"label":"humour","frequency":1,"documentFrequency":1,"idf":1.6582280766035324,"absoluteTfIdf":1.6582280766035324,"relativeTfIdf":0.0013899648588462134},{"label":"thence","frequency":1,"documentFrequency":1,"idf":1.6582280766035324,"absoluteTfIdf":1.6582280766035324,"relativeTfIdf":0.0013899648588462134},{"label":"vulgar","frequency":1,"documentFrequency":1,"idf":1.6582280766035324,"absoluteTfIdf":1.6582280766035324,"relativeTfIdf":0.0013899648588462134},{"label":"talk","frequency":1,"documentFrequency":1,"idf":1.6471782404169475,"absoluteTfIdf":1.6471782404169475,"relativeTfIdf":0.0013807026323696123},{"label":"no","frequency":4,"documentFrequency":1,"idf":0.41023838686082204,"absoluteTfIdf":1.6409535474432881,"relativeTfIdf":0.0013754849517546423},{"label":"reject","frequency":1,"documentFrequency":1,"idf":1.6308291024154178,"absoluteTfIdf":1.6308291024154178,"relativeTfIdf":0.0013669984094010208},{"label":"loss","frequency":1,"documentFrequency":1,"idf":1.6254382537805416,"absoluteTfIdf":1.6254382537805416,"relativeTfIdf":0.0013624796762619796},{"label":"far","frequency":3,"documentFrequency":1,"idf":0.5376368812166474,"absoluteTfIdf":1.6129106436499423,"relativeTfIdf":0.0013519787457250145},{"label":"title","frequency":1,"documentFrequency":1,"idf":1.5833267684304144,"absoluteTfIdf":1.5833267684304144,"relativeTfIdf":0.0013271808620539936},{"label":"probable","frequency":1,"documentFrequency":1,"idf":1.5679811987557544,"absoluteTfIdf":1.5679811987557544,"relativeTfIdf":0.0013143178531062484},{"label":"nothing","frequency":3,"documentFrequency":1,"idf":0.5214640219710465,"absoluteTfIdf":1.5643920659131394,"relativeTfIdf":0.0013113093595248444},{"label":"therefore","frequency":3,"documentFrequency":1,"idf":0.5214640219710465,"absoluteTfIdf":1.5643920659131394,"relativeTfIdf":0.0013113093595248444},{"label":"along","frequency":1,"documentFrequency":1,"idf":1.5528675609457059,"absoluteTfIdf":1.5528675609457059,"relativeTfIdf":0.0013016492547742715},{"label":"nor","frequency":3,"documentFrequency":1,"idf":0.5161306759956839,"absoluteTfIdf":1.5483920279870516,"relativeTfIdf":0.0012978977602573778},{"label":"separate","frequency":1,"documentFrequency":1,"idf":1.547880019434667,"absoluteTfIdf":1.547880019434667,"relativeTfIdf":0.00129746858292931},{"label":"book","frequency":1,"documentFrequency":1,"idf":1.542917230092538,"absoluteTfIdf":1.542917230092538,"relativeTfIdf":0.0012933086589208198},{"label":"accord","frequency":2,"documentFrequency":1,"idf":0.7644102005814359,"absoluteTfIdf":1.5288204011628719,"relativeTfIdf":0.0012814923731457434},{"label":"always","frequency":2,"documentFrequency":1,"idf":0.7621400520468967,"absoluteTfIdf":1.5242801040937934,"relativeTfIdf":0.0012776865918640347},{"label":"effect","frequency":2,"documentFrequency":1,"idf":0.7621400520468967,"absoluteTfIdf":1.5242801040937934,"relativeTfIdf":0.0012776865918640347},{"label":"requisite","frequency":1,"documentFrequency":1,"idf":1.4945986528217303,"absoluteTfIdf":1.4945986528217303,"relativeTfIdf":0.0012528069177047195},{"label":"relate","frequency":1,"documentFrequency":1,"idf":1.4852089124718912,"absoluteTfIdf":1.4852089124718912,"relativeTfIdf":0.0012449362216864135},{"label":"beauty","frequency":1,"documentFrequency":1,"idf":1.48054689936608,"absoluteTfIdf":1.48054689936608,"relativeTfIdf":0.0012410284152272256},{"label":"comprehend","frequency":1,"documentFrequency":1,"idf":1.4759065198095778,"absoluteTfIdf":1.4759065198095778,"relativeTfIdf":0.0012371387425059329},{"label":"past","frequency":1,"documentFrequency":1,"idf":1.4759065198095778,"absoluteTfIdf":1.4759065198095778,"relativeTfIdf":0.0012371387425059329},{"label":"gain","frequency":1,"documentFrequency":1,"idf":1.4485075456214633,"absoluteTfIdf":1.4485075456214633,"relativeTfIdf":0.0012141722930607405},{"label":"absolute","frequency":1,"documentFrequency":1,"idf":1.444013156033624,"absoluteTfIdf":1.444013156033624,"relativeTfIdf":0.0012104049924841777},{"label":"attempt","frequency":1,"documentFrequency":1,"idf":1.444013156033624,"absoluteTfIdf":1.444013156033624,"relativeTfIdf":0.0012104049924841777},{"label":"assert","frequency":1,"documentFrequency":1,"idf":1.4395388756387029,"absoluteTfIdf":1.4395388756387029,"relativeTfIdf":0.001206654547894973},{"label":"fail","frequency":1,"documentFrequency":1,"idf":1.4350845252893227,"absoluteTfIdf":1.4350845252893227,"relativeTfIdf":0.0012029208091276803},{"label":"late","frequency":1,"documentFrequency":1,"idf":1.4350845252893227,"absoluteTfIdf":1.4350845252893227,"relativeTfIdf":0.0012029208091276803},{"label":"plainly","frequency":1,"documentFrequency":1,"idf":1.4306499282214569,"absoluteTfIdf":1.4306499282214569,"relativeTfIdf":0.0011992036280146327},{"label":"reflect","frequency":1,"documentFrequency":1,"idf":1.4306499282214569,"absoluteTfIdf":1.4306499282214569,"relativeTfIdf":0.0011992036280146327},{"label":"connection","frequency":1,"documentFrequency":1,"idf":1.4262349100123402,"absoluteTfIdf":1.4262349100123402,"relativeTfIdf":0.0011955028583506622},{"label":"obvious","frequency":1,"documentFrequency":1,"idf":1.4262349100123402,"absoluteTfIdf":1.4262349100123402,"relativeTfIdf":0.0011955028583506622},{"label":"philosophy","frequency":1,"documentFrequency":1,"idf":1.4218392985393018,"absoluteTfIdf":1.4218392985393018,"relativeTfIdf":0.0011918183558585933},{"label":"ever","frequency":2,"documentFrequency":1,"idf":0.7091475219063864,"absoluteTfIdf":1.4182950438127728,"relativeTfIdf":0.0011888474801448222},{"label":"give","frequency":3,"documentFrequency":1,"idf":0.4710623905939776,"absoluteTfIdf":1.4131871717819329,"relativeTfIdf":0.0011845659444944953},{"label":"duty","frequency":1,"documentFrequency":1,"idf":1.400146473928042,"absoluteTfIdf":1.400146473928042,"relativeTfIdf":0.0011736349320436228},{"label":"bestow","frequency":1,"documentFrequency":1,"idf":1.3958638121360414,"absoluteTfIdf":1.3958638121360414,"relativeTfIdf":0.0011700451065683498},{"label":"unless","frequency":1,"documentFrequency":1,"idf":1.3958638121360414,"absoluteTfIdf":1.3958638121360414,"relativeTfIdf":0.0011700451065683498},{"label":"dispute","frequency":1,"documentFrequency":1,"idf":1.3915994133495837,"absoluteTfIdf":1.3915994133495837,"relativeTfIdf":0.0011664705895637752},{"label":"self","frequency":1,"documentFrequency":1,"idf":1.3873531224681328,"absoluteTfIdf":1.3873531224681328,"relativeTfIdf":0.001162911251021067},{"label":"agreeable","frequency":1,"documentFrequency":1,"idf":1.3831247863586116,"absoluteTfIdf":1.3831247863586116,"relativeTfIdf":0.001159366962580563},{"label":"open","frequency":1,"documentFrequency":1,"idf":1.374721375562232,"absoluteTfIdf":1.374721375562232,"relativeTfIdf":0.0011523230306473026},{"label":"than","frequency":3,"documentFrequency":1,"idf":0.4542552722775963,"absoluteTfIdf":1.362765816832789,"relativeTfIdf":0.0011423016067332683},{"label":"power","frequency":2,"documentFrequency":1,"idf":0.6794843300828275,"absoluteTfIdf":1.358968660165655,"relativeTfIdf":0.001139118742804405},{"label":"show","frequency":2,"documentFrequency":1,"idf":0.6773988235918061,"absoluteTfIdf":1.3547976471836123,"relativeTfIdf":0.0011356225039259114},{"label":"without","frequency":3,"documentFrequency":1,"idf":0.44926773076655735,"absoluteTfIdf":1.347803192299672,"relativeTfIdf":0.001129759591198384},{"label":"also","frequency":2,"documentFrequency":1,"idf":0.6732408134431425,"absoluteTfIdf":1.346481626886285,"relativeTfIdf":0.0011286518247160813},{"label":"year","frequency":1,"documentFrequency":1,"idf":1.3297240096314962,"absoluteTfIdf":1.3297240096314962,"relativeTfIdf":0.0011146052050557387},{"label":"danger","frequency":1,"documentFrequency":1,"idf":1.3099213823353166,"absoluteTfIdf":1.3099213823353166,"relativeTfIdf":0.0010980061880430149},{"label":"society","frequency":1,"documentFrequency":1,"idf":1.3099213823353166,"absoluteTfIdf":1.3099213823353166,"relativeTfIdf":0.0010980061880430149},{"label":"support","frequency":1,"documentFrequency":1,"idf":1.3099213823353166,"absoluteTfIdf":1.3099213823353166,"relativeTfIdf":0.0010980061880430149},{"label":"explain","frequency":1,"documentFrequency":1,"idf":1.3060074830141803,"absoluteTfIdf":1.3060074830141803,"relativeTfIdf":0.001094725467740302},{"label":"advance","frequency":1,"documentFrequency":1,"idf":1.290503296478215,"absoluteTfIdf":1.290503296478215,"relativeTfIdf":0.0010817295024964082},{"label":"constitution","frequency":1,"documentFrequency":1,"idf":1.290503296478215,"absoluteTfIdf":1.290503296478215,"relativeTfIdf":0.0010817295024964082},{"label":"teach","frequency":1,"documentFrequency":1,"idf":1.2790308953159784,"absoluteTfIdf":1.2790308953159784,"relativeTfIdf":0.0010721130723520356},{"label":"what","frequency":3,"documentFrequency":1,"idf":0.42631590358835497,"absoluteTfIdf":1.2789477107650649,"relativeTfIdf":0.0010720433451509345},{"label":"shall","frequency":3,"documentFrequency":1,"idf":0.4230796548091466,"absoluteTfIdf":1.2692389644274398,"relativeTfIdf":0.001063905250986957},{"label":"now","frequency":2,"documentFrequency":1,"idf":0.6246482582062772,"absoluteTfIdf":1.2492965164125545,"relativeTfIdf":0.0010471890330365084},{"label":"if","frequency":3,"documentFrequency":1,"idf":0.41343327775734123,"absoluteTfIdf":1.2402998332720236,"relativeTfIdf":0.0010396478065985112},{"label":"at","frequency":3,"documentFrequency":1,"idf":0.41183455639364425,"absoluteTfIdf":1.2355036691809327,"relativeTfIdf":0.0010356275517023744},{"label":"there","frequency":3,"documentFrequency":1,"idf":0.40864476102554403,"absoluteTfIdf":1.225934283076632,"relativeTfIdf":0.0010276062724866991},{"label":"bad","frequency":1,"documentFrequency":1,"idf":1.2199731456723772,"absoluteTfIdf":1.2199731456723772,"relativeTfIdf":0.0010226095102031662},{"label":"kind","frequency":2,"documentFrequency":1,"idf":0.6070180268300066,"absoluteTfIdf":1.2140360536600132,"relativeTfIdf":0.001017632903319374},{"label":"ground","frequency":1,"documentFrequency":1,"idf":1.2057380298505052,"absoluteTfIdf":1.2057380298505052,"relativeTfIdf":0.001010677309178965},{"label":"foundation","frequency":1,"documentFrequency":1,"idf":1.1986957472250923,"absoluteTfIdf":1.1986957472250923,"relativeTfIdf":0.0010047743061400607},{"label":"afford","frequency":1,"documentFrequency":1,"idf":1.1951931166738903,"absoluteTfIdf":1.1951931166738903,"relativeTfIdf":0.0010018383207660438},{"label":"enter","frequency":1,"documentFrequency":1,"idf":1.1951931166738903,"absoluteTfIdf":1.1951931166738903,"relativeTfIdf":0.0010018383207660438},{"label":"justice","frequency":1,"documentFrequency":1,"idf":1.1951931166738903,"absoluteTfIdf":1.1951931166738903,"relativeTfIdf":0.0010018383207660438},{"label":"light","frequency":1,"documentFrequency":1,"idf":1.1951931166738903,"absoluteTfIdf":1.1951931166738903,"relativeTfIdf":0.0010018383207660438},{"label":"satisfy","frequency":1,"documentFrequency":1,"idf":1.1951931166738903,"absoluteTfIdf":1.1951931166738903,"relativeTfIdf":0.0010018383207660438},{"label":"thought`","frequency":1,"documentFrequency":1,"idf":1.181304004513223,"absoluteTfIdf":1.181304004513223,"relativeTfIdf":0.0009901961479574376},{"label":"place","frequency":2,"documentFrequency":1,"idf":0.585883714756033,"absoluteTfIdf":1.171767429512066,"relativeTfIdf":0.000982202371762},{"label":"something","frequency":1,"documentFrequency":1,"idf":1.1642095711539229,"absoluteTfIdf":1.1642095711539229,"relativeTfIdf":0.0009758672013025338},{"label":"mean","frequency":2,"documentFrequency":1,"idf":0.5801964956354433,"absoluteTfIdf":1.1603929912708866,"relativeTfIdf":0.0009726680563880021},{"label":"public","frequency":1,"documentFrequency":1,"idf":1.1540914409883383,"absoluteTfIdf":1.1540914409883383,"relativeTfIdf":0.0009673859522115158},{"label":"never","frequency":2,"documentFrequency":1,"idf":0.5745414381520985,"absoluteTfIdf":1.149082876304197,"relativeTfIdf":0.0009631876582600142},{"label":"will","frequency":3,"documentFrequency":1,"idf":0.3819346106979702,"absoluteTfIdf":1.1458038320939106,"relativeTfIdf":0.0009604390880921296},{"label":"argument","frequency":1,"documentFrequency":1,"idf":1.1178436505959972,"absoluteTfIdf":1.1178436505959972,"relativeTfIdf":0.000937002221790442},{"label":"appearance","frequency":1,"documentFrequency":1,"idf":1.089133544713566,"absoluteTfIdf":1.089133544713566,"relativeTfIdf":0.000912936751645906},{"label":"entirely","frequency":1,"documentFrequency":1,"idf":1.089133544713566,"absoluteTfIdf":1.089133544713566,"relativeTfIdf":0.000912936751645906},{"label":"none","frequency":1,"documentFrequency":1,"idf":1.0766333819493346,"absoluteTfIdf":1.0766333819493346,"relativeTfIdf":0.0009024588281218228},{"label":"lay","frequency":1,"documentFrequency":1,"idf":1.0704414117014134,"absoluteTfIdf":1.0704414117014134,"relativeTfIdf":0.0008972685764471193},{"label":"point","frequency":1,"documentFrequency":1,"idf":1.0704414117014134,"absoluteTfIdf":1.0704414117014134,"relativeTfIdf":0.0008972685764471193},{"label":"look","frequency":1,"documentFrequency":1,"idf":1.052092273033217,"absoluteTfIdf":1.052092273033217,"relativeTfIdf":0.0008818879069850938},{"label":"lose","frequency":1,"documentFrequency":1,"idf":1.0340737675305385,"absoluteTfIdf":1.0340737675305385,"relativeTfIdf":0.0008667843818361597},{"label":"hear","frequency":1,"documentFrequency":1,"idf":1.031101997141381,"absoluteTfIdf":1.031101997141381,"relativeTfIdf":0.0008642933756423982},{"label":"remain","frequency":1,"documentFrequency":1,"idf":1.031101997141381,"absoluteTfIdf":1.031101997141381,"relativeTfIdf":0.0008642933756423982},{"label":"judgment","frequency":1,"documentFrequency":1,"idf":1.0251848201132925,"absoluteTfIdf":1.0251848201132925,"relativeTfIdf":0.0008593334619558194},{"label":"why","frequency":1,"documentFrequency":1,"idf":1.0193024502102261,"absoluteTfIdf":1.0193024502102261,"relativeTfIdf":0.0008544027244008601},{"label":"think","frequency":2,"documentFrequency":1,"idf":0.5037957178377326,"absoluteTfIdf":1.0075914356754652,"relativeTfIdf":0.0008445862830473304},{"label":"possible","frequency":1,"documentFrequency":1,"idf":1.0047461524360184,"absoluteTfIdf":1.0047461524360184,"relativeTfIdf":0.0008422013012875258},{"label":"part","frequency":2,"documentFrequency":1,"idf":0.5020459361139449,"absoluteTfIdf":1.0040918722278898,"relativeTfIdf":0.0008416528685900166},{"label":"discover","frequency":1,"documentFrequency":1,"idf":0.9932517730102834,"absoluteTfIdf":0.9932517730102834,"relativeTfIdf":0.0008325664484579074},{"label":"interest","frequency":1,"documentFrequency":1,"idf":0.9734491457141037,"absoluteTfIdf":0.9734491457141037,"relativeTfIdf":0.0008159674314451833},{"label":"rest","frequency":1,"documentFrequency":1,"idf":0.9512875739112513,"absoluteTfIdf":0.9512875739112513,"relativeTfIdf":0.0007973910929683582},{"label":"turn","frequency":1,"documentFrequency":1,"idf":0.9485515940923764,"absoluteTfIdf":0.9485515940923764,"relativeTfIdf":0.0007950977318460825},{"label":"begin","frequency":1,"documentFrequency":1,"idf":0.9458230794391724,"absoluteTfIdf":0.9458230794391724,"relativeTfIdf":0.0007928106281971269},{"label":"reason","frequency":2,"documentFrequency":1,"idf":0.4693689100876446,"absoluteTfIdf":0.9387378201752892,"relativeTfIdf":0.000786871601152799},{"label":"human","frequency":1,"documentFrequency":1,"idf":0.9349828648863077,"absoluteTfIdf":0.9349828648863077,"relativeTfIdf":0.0007837241113883551},{"label":"strong","frequency":1,"documentFrequency":1,"idf":0.9349828648863077,"absoluteTfIdf":0.9349828648863077,"relativeTfIdf":0.0007837241113883551},{"label":"desire","frequency":1,"documentFrequency":1,"idf":0.9296065078499273,"absoluteTfIdf":0.9296065078499273,"relativeTfIdf":0.0007792175254400061},{"label":"about","frequency":1,"documentFrequency":1,"idf":0.9189397400457321,"absoluteTfIdf":0.9189397400457321,"relativeTfIdf":0.0007702763956795743},{"label":"alone","frequency":1,"documentFrequency":1,"idf":0.9189397400457321,"absoluteTfIdf":0.9189397400457321,"relativeTfIdf":0.0007702763956795743},{"label":"just","frequency":1,"documentFrequency":1,"idf":0.9031499383130968,"absoluteTfIdf":0.9031499383130968,"relativeTfIdf":0.0007570410212180191},{"label":"please","frequency":1,"documentFrequency":1,"idf":0.8901795878704692,"absoluteTfIdf":0.8901795878704692,"relativeTfIdf":0.0007461689755829583},{"label":"idea","frequency":1,"documentFrequency":1,"idf":0.8876055838752964,"absoluteTfIdf":0.8876055838752964,"relativeTfIdf":0.0007440113863162585},{"label":"together","frequency":1,"documentFrequency":1,"idf":0.8799230877032802,"absoluteTfIdf":0.8799230877032802,"relativeTfIdf":0.0007375717415786088},{"label":"go","frequency":1,"documentFrequency":1,"idf":0.8773753156244816,"absoluteTfIdf":0.8773753156244816,"relativeTfIdf":0.0007354361405066904},{"label":"same","frequency":2,"documentFrequency":1,"idf":0.4328199915575313,"absoluteTfIdf":0.8656399831150626,"relativeTfIdf":0.0007255993152682839},{"label":"when","frequency":2,"documentFrequency":1,"idf":0.4311899993466003,"absoluteTfIdf":0.8623799986932006,"relativeTfIdf":0.0007228667214528086},{"label":"easily","frequency":1,"documentFrequency":1,"idf":0.8572235001871735,"absoluteTfIdf":0.8572235001871735,"relativeTfIdf":0.0007185444259741606},{"label":"hand","frequency":1,"documentFrequency":1,"idf":0.8547328388747217,"absoluteTfIdf":0.8547328388747217,"relativeTfIdf":0.0007164566964582747},{"label":"who","frequency":2,"documentFrequency":1,"idf":0.4230796548091466,"absoluteTfIdf":0.8461593096182932,"relativeTfIdf":0.0007092701673246381},{"label":"proceed","frequency":1,"documentFrequency":1,"idf":0.8253189536684283,"absoluteTfIdf":0.8253189536684283,"relativeTfIdf":0.0006918013023205602},{"label":"opinion","frequency":1,"documentFrequency":1,"idf":0.8229064072630444,"absoluteTfIdf":0.8229064072630444,"relativeTfIdf":0.0006897790505138679},{"label":"such","frequency":2,"documentFrequency":1,"idf":0.40864476102554403,"absoluteTfIdf":0.8172895220510881,"relativeTfIdf":0.0006850708483244661},{"label":"word","frequency":1,"documentFrequency":1,"idf":0.8038127484474646,"absoluteTfIdf":0.8038127484474646,"relativeTfIdf":0.0006737743071646812},{"label":"principle","frequency":1,"documentFrequency":1,"idf":0.7944009142651182,"absoluteTfIdf":0.7944009142651182,"relativeTfIdf":0.0006658850915885315},{"label":"form","frequency":1,"documentFrequency":1,"idf":0.7897280085657259,"absoluteTfIdf":0.7897280085657259,"relativeTfIdf":0.0006619681547072304},{"label":"one","frequency":2,"documentFrequency":1,"idf":0.39128047311620795,"absoluteTfIdf":0.7825609462324159,"relativeTfIdf":0.0006559605584513126},{"label":"action","frequency":1,"documentFrequency":1,"idf":0.7463916950787576,"absoluteTfIdf":0.7463916950787576,"relativeTfIdf":0.0006256426614239376},{"label":"perhaps","frequency":1,"documentFrequency":1,"idf":0.7352928020107088,"absoluteTfIdf":0.7352928020107088,"relativeTfIdf":0.0006163393143425891},{"label":"among","frequency":1,"documentFrequency":1,"idf":0.7286921179793566,"absoluteTfIdf":0.7286921179793566,"relativeTfIdf":0.000610806469387558},{"label":"body","frequency":1,"documentFrequency":1,"idf":0.7286921179793566,"absoluteTfIdf":0.7286921179793566,"relativeTfIdf":0.000610806469387558},{"label":"since","frequency":1,"documentFrequency":1,"idf":0.7243157433795577,"absoluteTfIdf":0.7243157433795577,"relativeTfIdf":0.0006071380916844575},{"label":"follow","frequency":1,"documentFrequency":1,"idf":0.7199584380106021,"absoluteTfIdf":0.7199584380106021,"relativeTfIdf":0.0006034856982486187},{"label":"understand","frequency":1,"documentFrequency":1,"idf":0.7156200364120039,"absoluteTfIdf":0.7156200364120039,"relativeTfIdf":0.0005998491503872623},{"label":"order","frequency":1,"documentFrequency":1,"idf":0.7134578734075088,"absoluteTfIdf":0.7134578734075088,"relativeTfIdf":0.0005980367756978279},{"label":"under","frequency":1,"documentFrequency":1,"idf":0.7113003752674875,"absoluteTfIdf":0.7113003752674875,"relativeTfIdf":0.0005962283112049351},{"label":"between","frequency":1,"documentFrequency":1,"idf":0.7091475219063864,"absoluteTfIdf":0.7091475219063864,"relativeTfIdf":0.0005944237400724111},{"label":"here","frequency":1,"documentFrequency":1,"idf":0.6963268334773252,"absoluteTfIdf":0.6963268334773252,"relativeTfIdf":0.0005836771445744553},{"label":"natural","frequency":1,"documentFrequency":1,"idf":0.6963268334773252,"absoluteTfIdf":0.6963268334773252,"relativeTfIdf":0.0005836771445744553},{"label":"suppose","frequency":1,"documentFrequency":1,"idf":0.6899776057986663,"absoluteTfIdf":0.6899776057986663,"relativeTfIdf":0.0005783550761095274},{"label":"case","frequency":1,"documentFrequency":1,"idf":0.6794843300828275,"absoluteTfIdf":0.6794843300828275,"relativeTfIdf":0.0005695593714022025},{"label":"thus","frequency":1,"documentFrequency":1,"idf":0.6711682738411701,"absoluteTfIdf":0.6711682738411701,"relativeTfIdf":0.0005625886620630093},{"label":"concern","frequency":1,"documentFrequency":1,"idf":0.6446090007688153,"absoluteTfIdf":0.6446090007688153,"relativeTfIdf":0.000540326069378722},{"label":"like","frequency":1,"documentFrequency":1,"idf":0.6405848504690899,"absoluteTfIdf":0.6405848504690899,"relativeTfIdf":0.0005369529341735875},{"label":"certain","frequency":1,"documentFrequency":1,"idf":0.6148153372900383,"absoluteTfIdf":0.6148153372900383,"relativeTfIdf":0.0005153523363705267},{"label":"see","frequency":1,"documentFrequency":1,"idf":0.585883714756033,"absoluteTfIdf":0.585883714756033,"relativeTfIdf":0.000491101185881},{"label":"even","frequency":1,"documentFrequency":1,"idf":0.5801964956354433,"absoluteTfIdf":0.5801964956354433,"relativeTfIdf":0.00048633402819400106},{"label":"another","frequency":1,"documentFrequency":1,"idf":0.5614693565847456,"absoluteTfIdf":0.5614693565847456,"relativeTfIdf":0.00047063651012971134},{"label":"less","frequency":1,"documentFrequency":1,"idf":0.5522356806378002,"absoluteTfIdf":0.5522356806378002,"relativeTfIdf":0.00046289663087829017},{"label":"say","frequency":1,"documentFrequency":1,"idf":0.5503991328304987,"absoluteTfIdf":0.5503991328304987,"relativeTfIdf":0.00046135719432564853},{"label":"time","frequency":1,"documentFrequency":1,"idf":0.5467361250717615,"absoluteTfIdf":0.5467361250717615,"relativeTfIdf":0.00045828677709284284},{"label":"own","frequency":1,"documentFrequency":1,"idf":0.5286196875664587,"absoluteTfIdf":0.5286196875664587,"relativeTfIdf":0.0004431011630900744},{"label":"take","frequency":1,"documentFrequency":1,"idf":0.5161306759956839,"absoluteTfIdf":0.5161306759956839,"relativeTfIdf":0.00043263258675245924},{"label":"good","frequency":1,"documentFrequency":1,"idf":0.4950772667978515,"absoluteTfIdf":0.4950772667978515,"relativeTfIdf":0.00041498513562267524},{"label":"much","frequency":1,"documentFrequency":1,"idf":0.48815682395327775,"absoluteTfIdf":0.48815682395327775,"relativeTfIdf":0.00040918426148640213},{"label":"into","frequency":1,"documentFrequency":1,"idf":0.4761601076656463,"absoluteTfIdf":0.4761601076656463,"relativeTfIdf":0.00039912833836181584},{"label":"though","frequency":1,"documentFrequency":1,"idf":0.4592678141011407,"absoluteTfIdf":0.4592678141011407,"relativeTfIdf":0.0003849688299255161},{"label":"some","frequency":1,"documentFrequency":1,"idf":0.4230796548091466,"absoluteTfIdf":0.4230796548091466,"relativeTfIdf":0.00035463508366231905},{"label":"make","frequency":1,"documentFrequency":1,"idf":0.40864476102554403,"absoluteTfIdf":0.40864476102554403,"relativeTfIdf":0.00034253542416223305},{"label":"so","frequency":1,"documentFrequency":1,"idf":0.3865966238037816,"absoluteTfIdf":0.3865966238037816,"relativeTfIdf":0.0003240541691565647}],"numbers":[],"names":[],"foreignText":[],"citations":[],"marginComments":[]}