{"id":"Shaftesbury.C.SC.3.1","documentCount":1,"importedDocumentCount":1,"wordCount":1705,"lemmaWordCount":1465,"numberWordCount":10,"nameWordCount":0,"foreignWordCount":214,"citationWordCount":16,"marginCommentWordCount":0,"lemmas":[{"label":"the","frequency":87,"documentFrequency":1,"idf":0.35290277801730885,"absoluteTfIdf":30.70254168750587,"relativeTfIdf":0.01800735582844919},{"label":"of","frequency":71,"documentFrequency":1,"idf":0.34989525695335355,"absoluteTfIdf":24.8425632436881,"relativeTfIdf":0.014570418324743754},{"label":"sensus","frequency":4,"documentFrequency":1,"idf":5.752572638825633,"absoluteTfIdf":23.010290555302532,"relativeTfIdf":0.013495771586687702},{"label":"and","frequency":64,"documentFrequency":1,"idf":0.3559193715567345,"absoluteTfIdf":22.778839779631006,"relativeTfIdf":0.013360023331161881},{"label":"salmasius","frequency":3,"documentFrequency":1,"idf":6.851184927493743,"absoluteTfIdf":20.55355478248123,"relativeTfIdf":0.012054870840164943},{"label":"be","frequency":55,"documentFrequency":1,"idf":0.3619799961684256,"absoluteTfIdf":19.90889978926341,"relativeTfIdf":0.011676774069949212},{"label":"satir","frequency":4,"documentFrequency":1,"idf":4.653960350157523,"absoluteTfIdf":18.615841400630092,"relativeTfIdf":0.010918382053155479},{"label":"communis","frequency":3,"documentFrequency":1,"idf":5.464890566373852,"absoluteTfIdf":16.394671699121556,"relativeTfIdf":0.009615643225291235},{"label":"a","frequency":39,"documentFrequency":1,"idf":0.35743108764205644,"absoluteTfIdf":13.939812418040201,"relativeTfIdf":0.008175843060434135},{"label":"gataker","frequency":2,"documentFrequency":1,"idf":6.851184927493743,"absoluteTfIdf":13.702369854987486,"relativeTfIdf":0.008036580560109963},{"label":"in","frequency":36,"documentFrequency":1,"idf":0.35743108764205644,"absoluteTfIdf":12.867519155114032,"relativeTfIdf":0.007546932055785356},{"label":"capitolinus","frequency":2,"documentFrequency":1,"idf":6.158037746933798,"absoluteTfIdf":12.316075493867595,"relativeTfIdf":0.007223504688485393},{"label":"to","frequency":34,"documentFrequency":1,"idf":0.35290277801730885,"absoluteTfIdf":11.9986944525885,"relativeTfIdf":0.007037357450198535},{"label":"he","frequency":26,"documentFrequency":1,"idf":0.41663840870628954,"absoluteTfIdf":10.832598626363527,"relativeTfIdf":0.006353430279392098},{"label":"ant","frequency":2,"documentFrequency":1,"idf":5.241747015059643,"absoluteTfIdf":10.483494030119285,"relativeTfIdf":0.0061486768505098445},{"label":"they","frequency":28,"documentFrequency":1,"idf":0.37421256460405994,"absoluteTfIdf":10.477951808913678,"relativeTfIdf":0.006145426280887788},{"label":"horace","frequency":3,"documentFrequency":1,"idf":3.4838890975072685,"absoluteTfIdf":10.451667292521805,"relativeTfIdf":0.006130010142241528},{"label":"public","frequency":9,"documentFrequency":1,"idf":1.1540914409883383,"absoluteTfIdf":10.386822968895045,"relativeTfIdf":0.006091978280876859},{"label":"as","frequency":28,"documentFrequency":1,"idf":0.3696077982173117,"absoluteTfIdf":10.349018350084728,"relativeTfIdf":0.0060698054839206615},{"label":"government","frequency":8,"documentFrequency":1,"idf":1.2490661066140418,"absoluteTfIdf":9.992528852912335,"relativeTfIdf":0.005860720734845944},{"label":"poet","frequency":5,"documentFrequency":1,"idf":1.9759876042925912,"absoluteTfIdf":9.879938021462957,"relativeTfIdf":0.005794685056576514},{"label":"withal","frequency":3,"documentFrequency":1,"idf":2.8808930139416207,"absoluteTfIdf":8.642679041824863,"relativeTfIdf":0.0050690199658796845},{"label":"commentator","frequency":2,"documentFrequency":1,"idf":4.143134726391533,"absoluteTfIdf":8.286269452783065,"relativeTfIdf":0.004859982083743733},{"label":"interpret","frequency":3,"documentFrequency":1,"idf":2.7403110633204313,"absoluteTfIdf":8.220933189961293,"relativeTfIdf":0.004821661694991961},{"label":"or","frequency":21,"documentFrequency":1,"idf":0.3788386329928422,"absoluteTfIdf":7.955611292849686,"relativeTfIdf":0.004666047679090725},{"label":"sense","frequency":12,"documentFrequency":1,"idf":0.642594901397114,"absoluteTfIdf":7.711138816765367,"relativeTfIdf":0.004522662062618984},{"label":"community","frequency":3,"documentFrequency":1,"idf":2.5204515872074116,"absoluteTfIdf":7.561354761622235,"relativeTfIdf":0.004434812176904537},{"label":"m","frequency":2,"documentFrequency":1,"idf":3.760142474135427,"absoluteTfIdf":7.520284948270854,"relativeTfIdf":0.004410724309836278},{"label":"have","frequency":20,"documentFrequency":1,"idf":0.3680775760365441,"absoluteTfIdf":7.361551520730883,"relativeTfIdf":0.004317625525355356},{"label":"nero","frequency":2,"documentFrequency":1,"idf":3.6731310971457973,"absoluteTfIdf":7.346262194291595,"relativeTfIdf":0.004308658178470143},{"label":"philosophy","frequency":5,"documentFrequency":1,"idf":1.4218392985393018,"absoluteTfIdf":7.109196492696509,"relativeTfIdf":0.004169616711258949},{"label":"apublick","frequency":1,"documentFrequency":1,"idf":6.851184927493743,"absoluteTfIdf":6.851184927493743,"relativeTfIdf":0.004018290280054982},{"label":"casaubons","frequency":1,"documentFrequency":1,"idf":6.851184927493743,"absoluteTfIdf":6.851184927493743,"relativeTfIdf":0.004018290280054982},{"label":"crispinus","frequency":1,"documentFrequency":1,"idf":6.851184927493743,"absoluteTfIdf":6.851184927493743,"relativeTfIdf":0.004018290280054982},{"label":"femaliz'd","frequency":1,"documentFrequency":1,"idf":6.851184927493743,"absoluteTfIdf":6.851184927493743,"relativeTfIdf":0.004018290280054982},{"label":"foster-father","frequency":1,"documentFrequency":1,"idf":6.851184927493743,"absoluteTfIdf":6.851184927493743,"relativeTfIdf":0.004018290280054982},{"label":"herodianus","frequency":1,"documentFrequency":1,"idf":6.851184927493743,"absoluteTfIdf":6.851184927493743,"relativeTfIdf":0.004018290280054982},{"label":"lambin","frequency":1,"documentFrequency":1,"idf":6.851184927493743,"absoluteTfIdf":6.851184927493743,"relativeTfIdf":0.004018290280054982},{"label":"magistracys","frequency":1,"documentFrequency":1,"idf":6.851184927493743,"absoluteTfIdf":6.851184927493743,"relativeTfIdf":0.004018290280054982},{"label":"puffed-up","frequency":1,"documentFrequency":1,"idf":6.851184927493743,"absoluteTfIdf":6.851184927493743,"relativeTfIdf":0.004018290280054982},{"label":"relationship","frequency":1,"documentFrequency":1,"idf":6.851184927493743,"absoluteTfIdf":6.851184927493743,"relativeTfIdf":0.004018290280054982},{"label":"slave-subjects","frequency":1,"documentFrequency":1,"idf":6.851184927493743,"absoluteTfIdf":6.851184927493743,"relativeTfIdf":0.004018290280054982},{"label":"vit","frequency":1,"documentFrequency":1,"idf":6.851184927493743,"absoluteTfIdf":6.851184927493743,"relativeTfIdf":0.004018290280054982},{"label":"it","frequency":18,"documentFrequency":1,"idf":0.3696077982173117,"absoluteTfIdf":6.652940367911611,"relativeTfIdf":0.0039020178110918536},{"label":"that","frequency":18,"documentFrequency":1,"idf":0.3696077982173117,"absoluteTfIdf":6.652940367911611,"relativeTfIdf":0.0039020178110918536},{"label":"this","frequency":18,"documentFrequency":1,"idf":0.3665496918584909,"absoluteTfIdf":6.597894453452836,"relativeTfIdf":0.003869732817274391},{"label":"word","frequency":8,"documentFrequency":1,"idf":0.8038127484474646,"absoluteTfIdf":6.430501987579717,"relativeTfIdf":0.003771555417935318},{"label":"prince","frequency":4,"documentFrequency":1,"idf":1.5781853689299958,"absoluteTfIdf":6.312741475719983,"relativeTfIdf":0.0037024876690439786},{"label":"we","frequency":16,"documentFrequency":1,"idf":0.3865966238037816,"absoluteTfIdf":6.185545980860506,"relativeTfIdf":0.003627886205783288},{"label":"aconstitution","frequency":1,"documentFrequency":1,"idf":6.158037746933798,"absoluteTfIdf":6.158037746933798,"relativeTfIdf":0.0036117523442426966},{"label":"casaubon","frequency":1,"documentFrequency":1,"idf":6.158037746933798,"absoluteTfIdf":6.158037746933798,"relativeTfIdf":0.0036117523442426966},{"label":"court-education","frequency":1,"documentFrequency":1,"idf":6.158037746933798,"absoluteTfIdf":6.158037746933798,"relativeTfIdf":0.0036117523442426966},{"label":"inf","frequency":1,"documentFrequency":1,"idf":6.158037746933798,"absoluteTfIdf":6.158037746933798,"relativeTfIdf":0.0036117523442426966},{"label":"mer","frequency":1,"documentFrequency":1,"idf":6.158037746933798,"absoluteTfIdf":6.158037746933798,"relativeTfIdf":0.0036117523442426966},{"label":"obligingness","frequency":1,"documentFrequency":1,"idf":6.158037746933798,"absoluteTfIdf":6.158037746933798,"relativeTfIdf":0.0036117523442426966},{"label":"unobserv'd","frequency":1,"documentFrequency":1,"idf":6.158037746933798,"absoluteTfIdf":6.158037746933798,"relativeTfIdf":0.0036117523442426966},{"label":"majority","frequency":2,"documentFrequency":1,"idf":3.044522437723423,"absoluteTfIdf":6.089044875446846,"relativeTfIdf":0.0035712873169776223},{"label":"dispense","frequency":2,"documentFrequency":1,"idf":3.001037325783684,"absoluteTfIdf":6.002074651567368,"relativeTfIdf":0.003520278388016052},{"label":"annotations","frequency":1,"documentFrequency":1,"idf":5.752572638825633,"absoluteTfIdf":5.752572638825633,"relativeTfIdf":0.0033739428966719255},{"label":"commonsense","frequency":1,"documentFrequency":1,"idf":5.752572638825633,"absoluteTfIdf":5.752572638825633,"relativeTfIdf":0.0033739428966719255},{"label":"dam","frequency":1,"documentFrequency":1,"idf":5.752572638825633,"absoluteTfIdf":5.752572638825633,"relativeTfIdf":0.0033739428966719255},{"label":"derivation","frequency":1,"documentFrequency":1,"idf":5.752572638825633,"absoluteTfIdf":5.752572638825633,"relativeTfIdf":0.0033739428966719255},{"label":"mimick","frequency":1,"documentFrequency":1,"idf":5.752572638825633,"absoluteTfIdf":5.752572638825633,"relativeTfIdf":0.0033739428966719255},{"label":"model'd","frequency":1,"documentFrequency":1,"idf":5.752572638825633,"absoluteTfIdf":5.752572638825633,"relativeTfIdf":0.0033739428966719255},{"label":"rudely","frequency":1,"documentFrequency":1,"idf":5.752572638825633,"absoluteTfIdf":5.752572638825633,"relativeTfIdf":0.0033739428966719255},{"label":"satirist","frequency":1,"documentFrequency":1,"idf":5.752572638825633,"absoluteTfIdf":5.752572638825633,"relativeTfIdf":0.0033739428966719255},{"label":"sociably","frequency":1,"documentFrequency":1,"idf":5.752572638825633,"absoluteTfIdf":5.752572638825633,"relativeTfIdf":0.0033739428966719255},{"label":"weal","frequency":1,"documentFrequency":1,"idf":5.752572638825633,"absoluteTfIdf":5.752572638825633,"relativeTfIdf":0.0033739428966719255},{"label":"humanity","frequency":3,"documentFrequency":1,"idf":1.8273044066474664,"absoluteTfIdf":5.481913219942399,"relativeTfIdf":0.003215198369467683},{"label":"assertors","frequency":1,"documentFrequency":1,"idf":5.464890566373852,"absoluteTfIdf":5.464890566373852,"relativeTfIdf":0.003205214408430412},{"label":"finem","frequency":1,"documentFrequency":1,"idf":5.464890566373852,"absoluteTfIdf":5.464890566373852,"relativeTfIdf":0.003205214408430412},{"label":"train'd","frequency":1,"documentFrequency":1,"idf":5.464890566373852,"absoluteTfIdf":5.464890566373852,"relativeTfIdf":0.003205214408430412},{"label":"affection","frequency":5,"documentFrequency":1,"idf":1.085993824708898,"absoluteTfIdf":5.42996912354449,"relativeTfIdf":0.0031847326237797596},{"label":"common","frequency":8,"documentFrequency":1,"idf":0.6711682738411701,"absoluteTfIdf":5.3693461907293605,"relativeTfIdf":0.00314917665145417},{"label":"allegiance","frequency":2,"documentFrequency":1,"idf":2.631677222317636,"absoluteTfIdf":5.263354444635272,"relativeTfIdf":0.0030870114044781656},{"label":"coinage","frequency":1,"documentFrequency":1,"idf":5.241747015059643,"absoluteTfIdf":5.241747015059643,"relativeTfIdf":0.0030743384252549222},{"label":"lineage","frequency":1,"documentFrequency":1,"idf":5.241747015059643,"absoluteTfIdf":5.241747015059643,"relativeTfIdf":0.0030743384252549222},{"label":"society","frequency":4,"documentFrequency":1,"idf":1.3099213823353166,"absoluteTfIdf":5.2396855293412665,"relativeTfIdf":0.0030731293427221505},{"label":"court","frequency":3,"documentFrequency":1,"idf":1.7452394535931621,"absoluteTfIdf":5.235718360779487,"relativeTfIdf":0.0030708025576419275},{"label":"it-self","frequency":2,"documentFrequency":1,"idf":2.6026896854443837,"absoluteTfIdf":5.2053793708887675,"relativeTfIdf":0.003053008428673764},{"label":"new-born","frequency":1,"documentFrequency":1,"idf":5.059425458265688,"absoluteTfIdf":5.059425458265688,"relativeTfIdf":0.002967404960859641},{"label":"satirical","frequency":1,"documentFrequency":1,"idf":5.059425458265688,"absoluteTfIdf":5.059425458265688,"relativeTfIdf":0.002967404960859641},{"label":"good","frequency":10,"documentFrequency":1,"idf":0.4950772667978515,"absoluteTfIdf":4.950772667978515,"relativeTfIdf":0.002903678984151622},{"label":"compact","frequency":1,"documentFrequency":1,"idf":4.90527477843843,"absoluteTfIdf":4.90527477843843,"relativeTfIdf":0.0028769940049492254},{"label":"executive","frequency":1,"documentFrequency":1,"idf":4.90527477843843,"absoluteTfIdf":4.90527477843843,"relativeTfIdf":0.0028769940049492254},{"label":"sharers","frequency":1,"documentFrequency":1,"idf":4.90527477843843,"absoluteTfIdf":4.90527477843843,"relativeTfIdf":0.0028769940049492254},{"label":"promise","frequency":3,"documentFrequency":1,"idf":1.6308291024154178,"absoluteTfIdf":4.892487307246253,"relativeTfIdf":0.00286949402184531},{"label":"moral","frequency":4,"documentFrequency":1,"idf":1.2199731456723772,"absoluteTfIdf":4.879892582689509,"relativeTfIdf":0.0028621070866214128},{"label":"young","frequency":3,"documentFrequency":1,"idf":1.6254382537805416,"absoluteTfIdf":4.876314761341625,"relativeTfIdf":0.0028600086576783725},{"label":"despotick","frequency":1,"documentFrequency":1,"idf":4.771743385813907,"absoluteTfIdf":4.771743385813907,"relativeTfIdf":0.0027986764726181273},{"label":"partnership","frequency":1,"documentFrequency":1,"idf":4.771743385813907,"absoluteTfIdf":4.771743385813907,"relativeTfIdf":0.0027986764726181273},{"label":"mankind","frequency":5,"documentFrequency":1,"idf":0.9431019893248118,"absoluteTfIdf":4.715509946624059,"relativeTfIdf":0.0027656949833572194},{"label":"state","frequency":5,"documentFrequency":1,"idf":0.9376819218554726,"absoluteTfIdf":4.688409609277363,"relativeTfIdf":0.002749800357347427},{"label":"civil","frequency":3,"documentFrequency":1,"idf":1.547880019434667,"absoluteTfIdf":4.643640058304001,"relativeTfIdf":0.0027235425561900296},{"label":"unapt","frequency":1,"documentFrequency":1,"idf":4.548599834499697,"absoluteTfIdf":4.548599834499697,"relativeTfIdf":0.0026678004894426376},{"label":"briton","frequency":1,"documentFrequency":1,"idf":4.453289654695372,"absoluteTfIdf":4.453289654695372,"relativeTfIdf":0.0026119000907304235},{"label":"debauch'd","frequency":1,"documentFrequency":1,"idf":4.453289654695372,"absoluteTfIdf":4.453289654695372,"relativeTfIdf":0.0026119000907304235},{"label":"juvenal","frequency":1,"documentFrequency":1,"idf":4.453289654695372,"absoluteTfIdf":4.453289654695372,"relativeTfIdf":0.0026119000907304235},{"label":"sub","frequency":1,"documentFrequency":1,"idf":4.453289654695372,"absoluteTfIdf":4.453289654695372,"relativeTfIdf":0.0026119000907304235},{"label":"lib","frequency":2,"documentFrequency":1,"idf":2.1877458333816757,"absoluteTfIdf":4.375491666763351,"relativeTfIdf":0.0025662707722952207},{"label":"fellowship","frequency":1,"documentFrequency":1,"idf":4.366278277705742,"absoluteTfIdf":4.366278277705742,"relativeTfIdf":0.002560867025047356},{"label":"tyranny","frequency":2,"documentFrequency":1,"idf":2.178356093031837,"absoluteTfIdf":4.356712186063674,"relativeTfIdf":0.0025552564141135916},{"label":"politic","frequency":2,"documentFrequency":1,"idf":2.169053700369523,"absoluteTfIdf":4.338107400739046,"relativeTfIdf":0.0025443445165624903},{"label":"omnipotence","frequency":1,"documentFrequency":1,"idf":4.286235570032206,"absoluteTfIdf":4.286235570032206,"relativeTfIdf":0.002513921155444109},{"label":"vers'd","frequency":1,"documentFrequency":1,"idf":4.286235570032206,"absoluteTfIdf":4.286235570032206,"relativeTfIdf":0.002513921155444109},{"label":"indulg'd","frequency":1,"documentFrequency":1,"idf":4.212127597878484,"absoluteTfIdf":4.212127597878484,"relativeTfIdf":0.0024704560691369407},{"label":"isaac","frequency":1,"documentFrequency":1,"idf":4.212127597878484,"absoluteTfIdf":4.212127597878484,"relativeTfIdf":0.0024704560691369407},{"label":"standard","frequency":2,"documentFrequency":1,"idf":2.089010992695987,"absoluteTfIdf":4.178021985391974,"relativeTfIdf":0.002450452777355996},{"label":"greek","frequency":2,"documentFrequency":1,"idf":2.080500303028078,"absoluteTfIdf":4.161000606056156,"relativeTfIdf":0.0024404695636693},{"label":"brutish","frequency":1,"documentFrequency":1,"idf":4.143134726391533,"absoluteTfIdf":4.143134726391533,"relativeTfIdf":0.0024299910418718665},{"label":"tiberius","frequency":1,"documentFrequency":1,"idf":4.143134726391533,"absoluteTfIdf":4.143134726391533,"relativeTfIdf":0.0024299910418718665},{"label":"toward","frequency":4,"documentFrequency":1,"idf":1.028139032010724,"absoluteTfIdf":4.112556128042896,"relativeTfIdf":0.00241205638008381},{"label":"sit","frequency":2,"documentFrequency":1,"idf":2.030903361888706,"absoluteTfIdf":4.061806723777412,"relativeTfIdf":0.00238229133359379},{"label":"how","frequency":6,"documentFrequency":1,"idf":0.6670360365562595,"absoluteTfIdf":4.002216219337557,"relativeTfIdf":0.0023473408911070717},{"label":"honestly","frequency":1,"documentFrequency":1,"idf":3.960813169597578,"absoluteTfIdf":3.960813169597578,"relativeTfIdf":0.0023230575774765855},{"label":"knave","frequency":1,"documentFrequency":1,"idf":3.960813169597578,"absoluteTfIdf":3.960813169597578,"relativeTfIdf":0.0023230575774765855},{"label":"partner","frequency":1,"documentFrequency":1,"idf":3.960813169597578,"absoluteTfIdf":3.960813169597578,"relativeTfIdf":0.0023230575774765855},{"label":"comment","frequency":1,"documentFrequency":1,"idf":3.9067459483273024,"absoluteTfIdf":3.9067459483273024,"relativeTfIdf":0.0022913465972594148},{"label":"immoderate","frequency":1,"documentFrequency":1,"idf":3.9067459483273024,"absoluteTfIdf":3.9067459483273024,"relativeTfIdf":0.0022913465972594148},{"label":"ridiculous","frequency":2,"documentFrequency":1,"idf":1.9459101490553132,"absoluteTfIdf":3.8918202981106265,"relativeTfIdf":0.0022825925502115113},{"label":"obligatory","frequency":1,"documentFrequency":1,"idf":3.855452653939752,"absoluteTfIdf":3.855452653939752,"relativeTfIdf":0.002261262553630353},{"label":"seneca","frequency":1,"documentFrequency":1,"idf":3.8066624897703196,"absoluteTfIdf":3.8066624897703196,"relativeTfIdf":0.0022326466215661697},{"label":"room","frequency":2,"documentFrequency":1,"idf":1.895357869892482,"absoluteTfIdf":3.790715739784964,"relativeTfIdf":0.0022232936890234393},{"label":"subsist","frequency":2,"documentFrequency":1,"idf":1.8744511850731684,"absoluteTfIdf":3.748902370146337,"relativeTfIdf":0.0021987697185609015},{"label":"contract","frequency":2,"documentFrequency":1,"idf":1.8675783057854063,"absoluteTfIdf":3.7351566115708126,"relativeTfIdf":0.0021907076900708577},{"label":"which","frequency":10,"documentFrequency":1,"idf":0.3696077982173117,"absoluteTfIdf":3.696077982173117,"relativeTfIdf":0.002167787672828808},{"label":"severe","frequency":2,"documentFrequency":1,"idf":1.8472386215482837,"absoluteTfIdf":3.6944772430965673,"relativeTfIdf":0.002166848822930538},{"label":"virtue","frequency":4,"documentFrequency":1,"idf":0.9162907318741551,"absoluteTfIdf":3.6651629274966204,"relativeTfIdf":0.002149655675951097},{"label":"adore","frequency":1,"documentFrequency":1,"idf":3.632309102625542,"absoluteTfIdf":3.632309102625542,"relativeTfIdf":0.002130386570454863},{"label":"early","frequency":2,"documentFrequency":1,"idf":1.8142323250801136,"absoluteTfIdf":3.628464650160227,"relativeTfIdf":0.002128131759624767},{"label":"free","frequency":3,"documentFrequency":1,"idf":1.2092778565556292,"absoluteTfIdf":3.6278335696668877,"relativeTfIdf":0.0021277616244380574},{"label":"hesitate","frequency":1,"documentFrequency":1,"idf":3.5930883894722605,"absoluteTfIdf":3.5930883894722605,"relativeTfIdf":0.0021073832196318244},{"label":"nicely","frequency":1,"documentFrequency":1,"idf":3.5553480614894135,"absoluteTfIdf":3.5553480614894135,"relativeTfIdf":0.0020852481299058145},{"label":"explanation","frequency":1,"documentFrequency":1,"idf":3.518980417318539,"absoluteTfIdf":3.518980417318539,"relativeTfIdf":0.002063918133324656},{"label":"natural","frequency":5,"documentFrequency":1,"idf":0.6963268334773252,"absoluteTfIdf":3.481634167386626,"relativeTfIdf":0.0020420141744203085},{"label":"rectitude","frequency":1,"documentFrequency":1,"idf":3.449987545831587,"absoluteTfIdf":3.449987545831587,"relativeTfIdf":0.002023453106059582},{"label":"epist","frequency":1,"documentFrequency":1,"idf":3.4171977230085964,"absoluteTfIdf":3.4171977230085964,"relativeTfIdf":0.002004221538421464},{"label":"power","frequency":5,"documentFrequency":1,"idf":0.6794843300828275,"absoluteTfIdf":3.3974216504141372,"relativeTfIdf":0.001992622668864597},{"label":"eastern","frequency":1,"documentFrequency":1,"idf":3.3546773660272624,"absoluteTfIdf":3.3546773660272624,"relativeTfIdf":0.001967552707347368},{"label":"notable","frequency":1,"documentFrequency":1,"idf":3.3546773660272624,"absoluteTfIdf":3.3546773660272624,"relativeTfIdf":0.001967552707347368},{"label":"perverted","frequency":1,"documentFrequency":1,"idf":3.3546773660272624,"absoluteTfIdf":3.3546773660272624,"relativeTfIdf":0.001967552707347368},{"label":"licentiousness","frequency":1,"documentFrequency":1,"idf":3.3248244028775815,"absoluteTfIdf":3.3248244028775815,"relativeTfIdf":0.0019500436380513674},{"label":"villainy","frequency":1,"documentFrequency":1,"idf":3.3248244028775815,"absoluteTfIdf":3.3248244028775815,"relativeTfIdf":0.0019500436380513674},{"label":"apprehend","frequency":2,"documentFrequency":1,"idf":1.6582280766035324,"absoluteTfIdf":3.316456153207065,"relativeTfIdf":0.0019451355737284837},{"label":"no","frequency":8,"documentFrequency":1,"idf":0.41023838686082204,"absoluteTfIdf":3.2819070948865763,"relativeTfIdf":0.0019248721964144142},{"label":"make","frequency":8,"documentFrequency":1,"idf":0.40864476102554403,"absoluteTfIdf":3.2691580882043523,"relativeTfIdf":0.0019173947731403827},{"label":"there","frequency":8,"documentFrequency":1,"idf":0.40864476102554403,"absoluteTfIdf":3.2691580882043523,"relativeTfIdf":0.0019173947731403827},{"label":"formation","frequency":1,"documentFrequency":1,"idf":3.2676659890376327,"absoluteTfIdf":3.2676659890376327,"relativeTfIdf":0.0019165196416643007},{"label":"can","frequency":8,"documentFrequency":1,"idf":0.3991359730565169,"absoluteTfIdf":3.193087784452135,"relativeTfIdf":0.0018727787592094634},{"label":"depress","frequency":1,"documentFrequency":1,"idf":3.1876232813640963,"absoluteTfIdf":3.1876232813640963,"relativeTfIdf":0.0018695737720610536},{"label":"mathematic","frequency":1,"documentFrequency":1,"idf":3.1623054733798064,"absoluteTfIdf":3.1623054733798064,"relativeTfIdf":0.0018547246178180683},{"label":"surrender","frequency":1,"documentFrequency":1,"idf":3.1623054733798064,"absoluteTfIdf":3.1623054733798064,"relativeTfIdf":0.0018547246178180683},{"label":"legislative","frequency":1,"documentFrequency":1,"idf":3.137612860789435,"absoluteTfIdf":3.137612860789435,"relativeTfIdf":0.0018402421470905777},{"label":"prompted","frequency":1,"documentFrequency":1,"idf":3.137612860789435,"absoluteTfIdf":3.137612860789435,"relativeTfIdf":0.0018402421470905777},{"label":"differently","frequency":1,"documentFrequency":1,"idf":3.1135153092103742,"absoluteTfIdf":3.1135153092103742,"relativeTfIdf":0.0018261086857538852},{"label":"manner","frequency":5,"documentFrequency":1,"idf":0.6167742017753713,"absoluteTfIdf":3.083871008876857,"relativeTfIdf":0.001808721999341265},{"label":"other","frequency":8,"documentFrequency":1,"idf":0.3850402032561233,"absoluteTfIdf":3.0803216260489865,"relativeTfIdf":0.0018066402498821035},{"label":"pag","frequency":1,"documentFrequency":1,"idf":3.0669952935754816,"absoluteTfIdf":3.0669952935754816,"relativeTfIdf":0.0017988242191058544},{"label":"will","frequency":8,"documentFrequency":1,"idf":0.3819346106979702,"absoluteTfIdf":3.0554768855837615,"relativeTfIdf":0.0017920685545945816},{"label":"for","frequency":8,"documentFrequency":1,"idf":0.3803854237111409,"absoluteTfIdf":3.0430833896891274,"relativeTfIdf":0.001784799642046409},{"label":"kind","frequency":5,"documentFrequency":1,"idf":0.6070180268300066,"absoluteTfIdf":3.035090134150033,"relativeTfIdf":0.001780111515630518},{"label":"disregard","frequency":1,"documentFrequency":1,"idf":3.022543531004648,"absoluteTfIdf":3.022543531004648,"relativeTfIdf":0.001772752804108298},{"label":"cicero","frequency":1,"documentFrequency":1,"idf":3.001037325783684,"absoluteTfIdf":3.001037325783684,"relativeTfIdf":0.001760139194008026},{"label":"interpretation","frequency":1,"documentFrequency":1,"idf":3.001037325783684,"absoluteTfIdf":3.001037325783684,"relativeTfIdf":0.001760139194008026},{"label":"on","frequency":7,"documentFrequency":1,"idf":0.42793796396022304,"absoluteTfIdf":2.995565747721561,"relativeTfIdf":0.0017569300573146986},{"label":"love","frequency":3,"documentFrequency":1,"idf":0.9875537518956456,"absoluteTfIdf":2.962661255686937,"relativeTfIdf":0.0017376312350070012},{"label":"who","frequency":7,"documentFrequency":1,"idf":0.4230796548091466,"absoluteTfIdf":2.9615575836640264,"relativeTfIdf":0.001736983920037552},{"label":"by","frequency":8,"documentFrequency":1,"idf":0.3696077982173117,"absoluteTfIdf":2.9568623857384937,"relativeTfIdf":0.0017342301382630462},{"label":"ordinarily","frequency":1,"documentFrequency":1,"idf":2.9391619220655967,"absoluteTfIdf":2.9391619220655967,"relativeTfIdf":0.0017238486346425788},{"label":"politeness","frequency":1,"documentFrequency":1,"idf":2.9391619220655967,"absoluteTfIdf":2.9391619220655967,"relativeTfIdf":0.0017238486346425788},{"label":"see","frequency":5,"documentFrequency":1,"idf":0.585883714756033,"absoluteTfIdf":2.929418573780165,"relativeTfIdf":0.0017181340608681318},{"label":"cherish","frequency":1,"documentFrequency":1,"idf":2.919359294769417,"absoluteTfIdf":2.919359294769417,"relativeTfIdf":0.0017122341904805963},{"label":"fashionable","frequency":1,"documentFrequency":1,"idf":2.8999412089123155,"absoluteTfIdf":2.8999412089123155,"relativeTfIdf":0.00170084528381954},{"label":"absolute","frequency":2,"documentFrequency":1,"idf":1.444013156033624,"absoluteTfIdf":2.888026312067248,"relativeTfIdf":0.0016938570745262452},{"label":"properly","frequency":2,"documentFrequency":1,"idf":1.4174629239395031,"absoluteTfIdf":2.8349258478790063,"relativeTfIdf":0.0016627131072604142},{"label":"etcetera","frequency":2,"documentFrequency":1,"idf":1.4131056185705473,"absoluteTfIdf":2.8262112371410946,"relativeTfIdf":0.0016576018986164778},{"label":"proud","frequency":1,"documentFrequency":1,"idf":2.8258332367585934,"absoluteTfIdf":2.8258332367585934,"relativeTfIdf":0.0016573801975123714},{"label":"rare","frequency":1,"documentFrequency":1,"idf":2.8258332367585934,"absoluteTfIdf":2.8258332367585934,"relativeTfIdf":0.0016573801975123714},{"label":"consider","frequency":5,"documentFrequency":1,"idf":0.5614693565847456,"absoluteTfIdf":2.807346782923728,"relativeTfIdf":0.001646537702594562},{"label":"duty","frequency":2,"documentFrequency":1,"idf":1.400146473928042,"absoluteTfIdf":2.800292947856084,"relativeTfIdf":0.001642400555927322},{"label":"confederacy","frequency":1,"documentFrequency":1,"idf":2.7907419169473235,"absoluteTfIdf":2.7907419169473235,"relativeTfIdf":0.001636798778268225},{"label":"real","frequency":3,"documentFrequency":1,"idf":0.9296065078499273,"absoluteTfIdf":2.788819523549782,"relativeTfIdf":0.001635671274809256},{"label":"mere","frequency":2,"documentFrequency":1,"idf":1.3873531224681328,"absoluteTfIdf":2.7747062449362656,"relativeTfIdf":0.0016273936920447305},{"label":"deference","frequency":1,"documentFrequency":1,"idf":2.7736474835880234,"absoluteTfIdf":2.7736474835880234,"relativeTfIdf":0.0016267727176469346},{"label":"latin","frequency":1,"documentFrequency":1,"idf":2.7403110633204313,"absoluteTfIdf":2.7403110633204313,"relativeTfIdf":0.0016072205649973203},{"label":"from","frequency":7,"documentFrequency":1,"idf":0.38971675114002524,"absoluteTfIdf":2.7280172579801767,"relativeTfIdf":0.0016000101219825083},{"label":"protect","frequency":1,"documentFrequency":1,"idf":2.7240505424486514,"absoluteTfIdf":2.7240505424486514,"relativeTfIdf":0.0015976836026091797},{"label":"may","frequency":7,"documentFrequency":1,"idf":0.38815547057307265,"absoluteTfIdf":2.7170882940115084,"relativeTfIdf":0.0015936001724407675},{"label":"just","frequency":3,"documentFrequency":1,"idf":0.9031499383130968,"absoluteTfIdf":2.7094498149392905,"relativeTfIdf":0.0015891201260640998},{"label":"courtiers","frequency":1,"documentFrequency":1,"idf":2.70805020110221,"absoluteTfIdf":2.70805020110221,"relativeTfIdf":0.0015882992381831143},{"label":"any","frequency":7,"documentFrequency":1,"idf":0.3850402032561233,"absoluteTfIdf":2.6952814227928634,"relativeTfIdf":0.0015808102186468406},{"label":"thank","frequency":1,"documentFrequency":1,"idf":2.6923018441340707,"absoluteTfIdf":2.6923018441340707,"relativeTfIdf":0.0015790626651812731},{"label":"reverse","frequency":1,"documentFrequency":1,"idf":2.661530185467317,"absoluteTfIdf":2.661530185467317,"relativeTfIdf":0.0015610147715350833},{"label":"thorough","frequency":1,"documentFrequency":1,"idf":2.661530185467317,"absoluteTfIdf":2.661530185467317,"relativeTfIdf":0.0015610147715350833},{"label":"man","frequency":6,"documentFrequency":1,"idf":0.4393666597838457,"absoluteTfIdf":2.636199958703074,"relativeTfIdf":0.0015461583335501902},{"label":"generally","frequency":2,"documentFrequency":1,"idf":1.3177954387662225,"absoluteTfIdf":2.635590877532445,"relativeTfIdf":0.0015458011011920498},{"label":"task","frequency":1,"documentFrequency":1,"idf":2.631677222317636,"absoluteTfIdf":2.631677222317636,"relativeTfIdf":0.0015435057022390828},{"label":"speak","frequency":3,"documentFrequency":1,"idf":0.8722991625926209,"absoluteTfIdf":2.6168974877778624,"relativeTfIdf":0.0015348372362333504},{"label":"honesty","frequency":1,"documentFrequency":1,"idf":2.6026896854443837,"absoluteTfIdf":2.6026896854443837,"relativeTfIdf":0.001526504214336882},{"label":"same","frequency":6,"documentFrequency":1,"idf":0.4328199915575313,"absoluteTfIdf":2.596919949345188,"relativeTfIdf":0.0015231202048945384},{"label":"selfish","frequency":1,"documentFrequency":1,"idf":2.588505050452427,"absoluteTfIdf":2.588505050452427,"relativeTfIdf":0.0015181847803240043},{"label":"unlimited","frequency":1,"documentFrequency":1,"idf":2.588505050452427,"absoluteTfIdf":2.588505050452427,"relativeTfIdf":0.0015181847803240043},{"label":"private","frequency":2,"documentFrequency":1,"idf":1.2866645201710494,"absoluteTfIdf":2.5733290403420988,"relativeTfIdf":0.001509283894628797},{"label":"above-mentioned","frequency":1,"documentFrequency":1,"idf":2.547119834289573,"absoluteTfIdf":2.547119834289573,"relativeTfIdf":0.0014939119262695442},{"label":"nature","frequency":5,"documentFrequency":1,"idf":0.5090635087725914,"absoluteTfIdf":2.545317543862957,"relativeTfIdf":0.001492854864435752},{"label":"civility","frequency":1,"documentFrequency":1,"idf":2.5204515872074116,"absoluteTfIdf":2.5204515872074116,"relativeTfIdf":0.0014782707256348455},{"label":"rigid","frequency":1,"documentFrequency":1,"idf":2.507379505640059,"absoluteTfIdf":2.507379505640059,"relativeTfIdf":0.001470603815624668},{"label":"refer","frequency":1,"documentFrequency":1,"idf":2.494476100804151,"absoluteTfIdf":2.494476100804151,"relativeTfIdf":0.001463035836248769},{"label":"rise","frequency":2,"documentFrequency":1,"idf":1.2380568211056726,"absoluteTfIdf":2.4761136422113452,"relativeTfIdf":0.0014522660658131056},{"label":"equality","frequency":1,"documentFrequency":1,"idf":2.469158292819861,"absoluteTfIdf":2.469158292819861,"relativeTfIdf":0.0014481866820057836},{"label":"head","frequency":2,"documentFrequency":1,"idf":1.2271674213064043,"absoluteTfIdf":2.4543348426128087,"relativeTfIdf":0.0014394925763124978},{"label":"such","frequency":6,"documentFrequency":1,"idf":0.40864476102554403,"absoluteTfIdf":2.451868566153264,"relativeTfIdf":0.001438046079855287},{"label":"legal","frequency":1,"documentFrequency":1,"idf":2.4444656802294897,"absoluteTfIdf":2.4444656802294897,"relativeTfIdf":0.001433704211278293},{"label":"social","frequency":1,"documentFrequency":1,"idf":2.4444656802294897,"absoluteTfIdf":2.4444656802294897,"relativeTfIdf":0.001433704211278293},{"label":"second","frequency":2,"documentFrequency":1,"idf":1.2163953243244932,"absoluteTfIdf":2.4327906486489863,"relativeTfIdf":0.0014268566854246255},{"label":"model","frequency":1,"documentFrequency":1,"idf":2.396837631240235,"absoluteTfIdf":2.396837631240235,"relativeTfIdf":0.0014057698716951523},{"label":"nobility","frequency":1,"documentFrequency":1,"idf":2.396837631240235,"absoluteTfIdf":2.396837631240235,"relativeTfIdf":0.0014057698716951523},{"label":"justice","frequency":2,"documentFrequency":1,"idf":1.1951931166738903,"absoluteTfIdf":2.3903862333477806,"relativeTfIdf":0.001401986060614534},{"label":"form","frequency":3,"documentFrequency":1,"idf":0.7897280085657259,"absoluteTfIdf":2.3691840256971775,"relativeTfIdf":0.0013895507482094883},{"label":"tyrant","frequency":1,"documentFrequency":1,"idf":2.362548557761603,"absoluteTfIdf":2.362548557761603,"relativeTfIdf":0.001385658978159298},{"label":"fame","frequency":1,"documentFrequency":1,"idf":2.3513752571634776,"absoluteTfIdf":2.3513752571634776,"relativeTfIdf":0.0013791057226765265},{"label":"mouth","frequency":1,"documentFrequency":1,"idf":2.3513752571634776,"absoluteTfIdf":2.3513752571634776,"relativeTfIdf":0.0013791057226765265},{"label":"country","frequency":2,"documentFrequency":1,"idf":1.1608254731696823,"absoluteTfIdf":2.3216509463393646,"relativeTfIdf":0.0013616721092899499},{"label":"ingenious","frequency":1,"documentFrequency":1,"idf":2.307890145223739,"absoluteTfIdf":2.307890145223739,"relativeTfIdf":0.0013536012581957413},{"label":"day","frequency":2,"documentFrequency":1,"idf":1.1474024528375417,"absoluteTfIdf":2.2948049056750834,"relativeTfIdf":0.0013459266308944772},{"label":"rights","frequency":1,"documentFrequency":1,"idf":2.2868367360259065,"absoluteTfIdf":2.2868367360259065,"relativeTfIdf":0.0013412532176105025},{"label":"equity","frequency":1,"documentFrequency":1,"idf":2.27647394899036,"absoluteTfIdf":2.27647394899036,"relativeTfIdf":0.0013351753366512373},{"label":"ancestor","frequency":1,"documentFrequency":1,"idf":2.2662174488231708,"absoluteTfIdf":2.2662174488231708,"relativeTfIdf":0.001329159794031185},{"label":"press","frequency":1,"documentFrequency":1,"idf":2.256065077359153,"absoluteTfIdf":2.256065077359153,"relativeTfIdf":0.0013232053239643124},{"label":"notion","frequency":2,"documentFrequency":1,"idf":1.127599825541362,"absoluteTfIdf":2.255199651082724,"relativeTfIdf":0.0013226977425705125},{"label":"without","frequency":5,"documentFrequency":1,"idf":0.44926773076655735,"absoluteTfIdf":2.2463386538327867,"relativeTfIdf":0.0013175006767347723},{"label":"many","frequency":6,"documentFrequency":1,"idf":0.3726752852851735,"absoluteTfIdf":2.236051711711041,"relativeTfIdf":0.0013114672795959184},{"label":"treatise","frequency":1,"documentFrequency":1,"idf":2.2164559392641072,"absoluteTfIdf":2.2164559392641072,"relativeTfIdf":0.0012999741579261626},{"label":"where","frequency":4,"documentFrequency":1,"idf":0.5540756075598073,"absoluteTfIdf":2.2163024302392293,"relativeTfIdf":0.0012998841233074659},{"label":"among","frequency":3,"documentFrequency":1,"idf":0.7286921179793566,"absoluteTfIdf":2.18607635393807,"relativeTfIdf":0.001282156219318516},{"label":"corruption","frequency":1,"documentFrequency":1,"idf":2.178356093031837,"absoluteTfIdf":2.178356093031837,"relativeTfIdf":0.0012776282070567958},{"label":"morality","frequency":1,"documentFrequency":1,"idf":2.178356093031837,"absoluteTfIdf":2.178356093031837,"relativeTfIdf":0.0012776282070567958},{"label":"barbarous","frequency":1,"documentFrequency":1,"idf":2.169053700369523,"absoluteTfIdf":2.169053700369523,"relativeTfIdf":0.0012721722582812451},{"label":"when","frequency":5,"documentFrequency":1,"idf":0.4311899993466003,"absoluteTfIdf":2.1559499967330016,"relativeTfIdf":0.0012644868016029333},{"label":"none","frequency":2,"documentFrequency":1,"idf":1.0766333819493346,"absoluteTfIdf":2.153266763898669,"relativeTfIdf":0.0012629130580050845},{"label":"under","frequency":3,"documentFrequency":1,"idf":0.7113003752674875,"absoluteTfIdf":2.1339011258024625,"relativeTfIdf":0.0012515549124941128},{"label":"what","frequency":5,"documentFrequency":1,"idf":0.42631590358835497,"absoluteTfIdf":2.1315795179417747,"relativeTfIdf":0.0012501932656549999},{"label":"learn","frequency":2,"documentFrequency":1,"idf":1.0642875461270351,"absoluteTfIdf":2.1285750922540703,"relativeTfIdf":0.0012484311391519473},{"label":"between","frequency":3,"documentFrequency":1,"idf":0.7091475219063864,"absoluteTfIdf":2.1274425657191594,"relativeTfIdf":0.0012477669007150494},{"label":"hardly","frequency":1,"documentFrequency":1,"idf":2.106252799130493,"absoluteTfIdf":2.106252799130493,"relativeTfIdf":0.0012353388851205236},{"label":"sacred","frequency":1,"documentFrequency":1,"idf":2.097594736387378,"absoluteTfIdf":2.097594736387378,"relativeTfIdf":0.0012302608424559402},{"label":"still","frequency":3,"documentFrequency":1,"idf":0.6942059419081874,"absoluteTfIdf":2.0826178257245624,"relativeTfIdf":0.0012214767306302418},{"label":"spirit","frequency":2,"documentFrequency":1,"idf":1.0400439345170422,"absoluteTfIdf":2.0800878690340845,"relativeTfIdf":0.0012199928850639792},{"label":"parent","frequency":1,"documentFrequency":1,"idf":2.0720614343822135,"absoluteTfIdf":2.0720614343822135,"relativeTfIdf":0.0012152852987578964},{"label":"measure","frequency":2,"documentFrequency":1,"idf":1.0251848201132925,"absoluteTfIdf":2.050369640226585,"relativeTfIdf":0.001202562838842572},{"label":"ballance","frequency":1,"documentFrequency":1,"idf":2.039000572121325,"absoluteTfIdf":2.039000572121325,"relativeTfIdf":0.001195894763707522},{"label":"endure","frequency":1,"documentFrequency":1,"idf":2.039000572121325,"absoluteTfIdf":2.039000572121325,"relativeTfIdf":0.001195894763707522},{"label":"personal","frequency":1,"documentFrequency":1,"idf":2.039000572121325,"absoluteTfIdf":2.039000572121325,"relativeTfIdf":0.001195894763707522},{"label":"why","frequency":2,"documentFrequency":1,"idf":1.0193024502102261,"absoluteTfIdf":2.0386049004204523,"relativeTfIdf":0.0011956626981938136},{"label":"show","frequency":3,"documentFrequency":1,"idf":0.6773988235918061,"absoluteTfIdf":2.0321964707754185,"relativeTfIdf":0.0011919040884313305},{"label":"censure","frequency":1,"documentFrequency":1,"idf":2.030903361888706,"absoluteTfIdf":2.030903361888706,"relativeTfIdf":0.001191145666796895},{"label":"vol","frequency":1,"documentFrequency":1,"idf":2.030903361888706,"absoluteTfIdf":2.030903361888706,"relativeTfIdf":0.001191145666796895},{"label":"knowledge","frequency":2,"documentFrequency":1,"idf":1.013454480327803,"absoluteTfIdf":2.026908960655606,"relativeTfIdf":0.0011888029094754286},{"label":"think","frequency":4,"documentFrequency":1,"idf":0.5037957178377326,"absoluteTfIdf":2.0151828713509303,"relativeTfIdf":0.001181925437742481},{"label":"protection","frequency":1,"documentFrequency":1,"idf":2.0149030205422647,"absoluteTfIdf":2.0149030205422647,"relativeTfIdf":0.0011817613023708297},{"label":"thus","frequency":3,"documentFrequency":1,"idf":0.6711682738411701,"absoluteTfIdf":2.0135048215235103,"relativeTfIdf":0.0011809412442953138},{"label":"before","frequency":3,"documentFrequency":1,"idf":0.6691000207771111,"absoluteTfIdf":2.0073000623313333,"relativeTfIdf":0.0011773020893438904},{"label":"scarcely","frequency":1,"documentFrequency":1,"idf":1.9991546635741255,"absoluteTfIdf":1.9991546635741255,"relativeTfIdf":0.0011725247293689885},{"label":"keep","frequency":2,"documentFrequency":1,"idf":0.9932517730102834,"absoluteTfIdf":1.986503546020567,"relativeTfIdf":0.0011651047190736463},{"label":"obey","frequency":1,"documentFrequency":1,"idf":1.9759876042925912,"absoluteTfIdf":1.9759876042925912,"relativeTfIdf":0.0011589370113153027},{"label":"p","frequency":1,"documentFrequency":1,"idf":1.9759876042925912,"absoluteTfIdf":1.9759876042925912,"relativeTfIdf":0.0011589370113153027},{"label":"law","frequency":2,"documentFrequency":1,"idf":0.9875537518956456,"absoluteTfIdf":1.9751075037912913,"relativeTfIdf":0.0011584208233380007},{"label":"rome","frequency":1,"documentFrequency":1,"idf":1.9683830049073718,"absoluteTfIdf":1.9683830049073718,"relativeTfIdf":0.0011544768357227987},{"label":"universe","frequency":1,"documentFrequency":1,"idf":1.960835799271989,"absoluteTfIdf":1.960835799271989,"relativeTfIdf":0.0011500503221536591},{"label":"increase","frequency":1,"documentFrequency":1,"idf":1.9533451275428313,"absoluteTfIdf":1.9533451275428313,"relativeTfIdf":0.0011456569663007808},{"label":"magistrate","frequency":1,"documentFrequency":1,"idf":1.9533451275428313,"absoluteTfIdf":1.9533451275428313,"relativeTfIdf":0.0011456569663007808},{"label":"interest","frequency":2,"documentFrequency":1,"idf":0.9734491457141037,"absoluteTfIdf":1.9468982914282074,"relativeTfIdf":0.0011418758307496818},{"label":"all","frequency":5,"documentFrequency":1,"idf":0.38815547057307265,"absoluteTfIdf":1.9407773528653633,"relativeTfIdf":0.001138285837457691},{"label":"right","frequency":2,"documentFrequency":1,"idf":0.9678625390054638,"absoluteTfIdf":1.9357250780109276,"relativeTfIdf":0.001135322626399371},{"label":"so","frequency":5,"documentFrequency":1,"idf":0.3865966238037816,"absoluteTfIdf":1.9329831190189082,"relativeTfIdf":0.0011337144393072775},{"label":"permit","frequency":1,"documentFrequency":1,"idf":1.9312040016656178,"absoluteTfIdf":1.9312040016656178,"relativeTfIdf":0.0011326709687188375},{"label":"sect","frequency":1,"documentFrequency":1,"idf":1.9312040016656178,"absoluteTfIdf":1.9312040016656178,"relativeTfIdf":0.0011326709687188375},{"label":"like","frequency":3,"documentFrequency":1,"idf":0.6405848504690899,"absoluteTfIdf":1.9217545514072696,"relativeTfIdf":0.0011271287691538238},{"label":"must","frequency":4,"documentFrequency":1,"idf":0.4795730802618863,"absoluteTfIdf":1.918292321047545,"relativeTfIdf":0.0011250981355117567},{"label":"admire","frequency":1,"documentFrequency":1,"idf":1.9095425048844383,"absoluteTfIdf":1.9095425048844383,"relativeTfIdf":0.0011199662785245973},{"label":"appoint","frequency":1,"documentFrequency":1,"idf":1.895357869892482,"absoluteTfIdf":1.895357869892482,"relativeTfIdf":0.0011116468445117197},{"label":"not","frequency":5,"documentFrequency":1,"idf":0.3788386329928422,"absoluteTfIdf":1.894193164964211,"relativeTfIdf":0.0011109637331168393},{"label":"obligation","frequency":1,"documentFrequency":1,"idf":1.8883402972338355,"absoluteTfIdf":1.8883402972338355,"relativeTfIdf":0.0011075309661195516},{"label":"arbitrary","frequency":1,"documentFrequency":1,"idf":1.8744511850731684,"absoluteTfIdf":1.8744511850731684,"relativeTfIdf":0.0010993848592804507},{"label":"succession","frequency":1,"documentFrequency":1,"idf":1.8744511850731684,"absoluteTfIdf":1.8744511850731684,"relativeTfIdf":0.0010993848592804507},{"label":"english","frequency":1,"documentFrequency":1,"idf":1.8675783057854063,"absoluteTfIdf":1.8675783057854063,"relativeTfIdf":0.0010953538450354289},{"label":"modern","frequency":1,"documentFrequency":1,"idf":1.8675783057854063,"absoluteTfIdf":1.8675783057854063,"relativeTfIdf":0.0010953538450354289},{"label":"ability","frequency":1,"documentFrequency":1,"idf":1.8607523407150066,"absoluteTfIdf":1.8607523407150066,"relativeTfIdf":0.0010913503464604144},{"label":"signify","frequency":1,"documentFrequency":1,"idf":1.8539726537296277,"absoluteTfIdf":1.8539726537296277,"relativeTfIdf":0.0010873739904572596},{"label":"accordingly","frequency":1,"documentFrequency":1,"idf":1.8472386215482837,"absoluteTfIdf":1.8472386215482837,"relativeTfIdf":0.001083424411465269},{"label":"upon","frequency":4,"documentFrequency":1,"idf":0.460944260428393,"absoluteTfIdf":1.843777041713572,"relativeTfIdf":0.0010813941593627988},{"label":"reader","frequency":1,"documentFrequency":1,"idf":1.8339050906788184,"absoluteTfIdf":1.8339050906788184,"relativeTfIdf":0.001075604158755905},{"label":"seem","frequency":3,"documentFrequency":1,"idf":0.6109090823229733,"absoluteTfIdf":1.8327272469689198,"relativeTfIdf":0.0010749133413307447},{"label":"act","frequency":2,"documentFrequency":1,"idf":0.9110136747733113,"absoluteTfIdf":1.8220273495466226,"relativeTfIdf":0.0010686377416695733},{"label":"seldom","frequency":1,"documentFrequency":1,"idf":1.8207470061013074,"absoluteTfIdf":1.8207470061013074,"relativeTfIdf":0.001067886807097541},{"label":"zeal","frequency":1,"documentFrequency":1,"idf":1.8207470061013074,"absoluteTfIdf":1.8207470061013074,"relativeTfIdf":0.001067886807097541},{"label":"than","frequency":4,"documentFrequency":1,"idf":0.4542552722775963,"absoluteTfIdf":1.8170210891103853,"relativeTfIdf":0.0010657015185398153},{"label":"deep","frequency":1,"documentFrequency":1,"idf":1.8142323250801136,"absoluteTfIdf":1.8142323250801136,"relativeTfIdf":0.0010640658798123834},{"label":"contempt","frequency":1,"documentFrequency":1,"idf":1.8013289202442055,"absoluteTfIdf":1.8013289202442055,"relativeTfIdf":0.0010564979004364843},{"label":"ii","frequency":1,"documentFrequency":1,"idf":1.7760111122599158,"absoluteTfIdf":1.7760111122599158,"relativeTfIdf":0.001041648746193499},{"label":"heaven","frequency":1,"documentFrequency":1,"idf":1.76978056250928,"absoluteTfIdf":1.76978056250928,"relativeTfIdf":0.001037994464814827},{"label":"together","frequency":2,"documentFrequency":1,"idf":0.8799230877032802,"absoluteTfIdf":1.7598461754065604,"relativeTfIdf":0.0010321678448132318},{"label":"even","frequency":3,"documentFrequency":1,"idf":0.5801964956354433,"absoluteTfIdf":1.7405894869063299,"relativeTfIdf":0.0010208735993585513},{"label":"wrong","frequency":1,"documentFrequency":1,"idf":1.7331911150769876,"absoluteTfIdf":1.7331911150769876,"relativeTfIdf":0.0010165343783442742},{"label":"never","frequency":3,"documentFrequency":1,"idf":0.5745414381520985,"absoluteTfIdf":1.7236243144562953,"relativeTfIdf":0.00101092335158727},{"label":"roman","frequency":1,"documentFrequency":1,"idf":1.7212862125706694,"absoluteTfIdf":1.7212862125706694,"relativeTfIdf":0.0010095520308332372},{"label":"weight","frequency":1,"documentFrequency":1,"idf":1.7095213709910828,"absoluteTfIdf":1.7095213709910828,"relativeTfIdf":0.0010026518304933037},{"label":"beside","frequency":2,"documentFrequency":1,"idf":0.8547328388747217,"absoluteTfIdf":1.7094656777494435,"relativeTfIdf":0.0010026191658354508},{"label":"some","frequency":4,"documentFrequency":1,"idf":0.4230796548091466,"absoluteTfIdf":1.6923186192365864,"relativeTfIdf":0.0009925622400214582},{"label":"faith","frequency":1,"documentFrequency":1,"idf":1.6921296282792138,"absoluteTfIdf":1.6921296282792138,"relativeTfIdf":0.0009924513948851694},{"label":"remarkable","frequency":1,"documentFrequency":1,"idf":1.6750351949199136,"absoluteTfIdf":1.6750351949199136,"relativeTfIdf":0.000982425334263879},{"label":"however","frequency":2,"documentFrequency":1,"idf":0.8350277677953892,"absoluteTfIdf":1.6700555355907785,"relativeTfIdf":0.0009795047129564684},{"label":"deserve","frequency":1,"documentFrequency":1,"idf":1.6694013772016576,"absoluteTfIdf":1.6694013772016576,"relativeTfIdf":0.0009791210423470132},{"label":"note","frequency":1,"documentFrequency":1,"idf":1.6694013772016576,"absoluteTfIdf":1.6694013772016576,"relativeTfIdf":0.0009791210423470132},{"label":"union","frequency":1,"documentFrequency":1,"idf":1.6694013772016576,"absoluteTfIdf":1.6694013772016576,"relativeTfIdf":0.0009791210423470132},{"label":"incline","frequency":1,"documentFrequency":1,"idf":1.6637991216529877,"absoluteTfIdf":1.6637991216529877,"relativeTfIdf":0.0009758352619665617},{"label":"humour","frequency":1,"documentFrequency":1,"idf":1.6582280766035324,"absoluteTfIdf":1.6582280766035324,"relativeTfIdf":0.0009725677868642419},{"label":"vulgar","frequency":1,"documentFrequency":1,"idf":1.6582280766035324,"absoluteTfIdf":1.6582280766035324,"relativeTfIdf":0.0009725677868642419},{"label":"if","frequency":4,"documentFrequency":1,"idf":0.41343327775734123,"absoluteTfIdf":1.653733111029365,"relativeTfIdf":0.0009699314434189824},{"label":"at","frequency":4,"documentFrequency":1,"idf":0.41183455639364425,"absoluteTfIdf":1.647338225574577,"relativeTfIdf":0.000966180777463095},{"label":"expression","frequency":1,"documentFrequency":1,"idf":1.6471782404169475,"absoluteTfIdf":1.6471782404169475,"relativeTfIdf":0.0009660869445260689},{"label":"viz","frequency":1,"documentFrequency":1,"idf":1.6254382537805416,"absoluteTfIdf":1.6254382537805416,"relativeTfIdf":0.0009533362192261242},{"label":"far","frequency":3,"documentFrequency":1,"idf":0.5376368812166474,"absoluteTfIdf":1.6129106436499423,"relativeTfIdf":0.000945988647302019},{"label":"passion","frequency":2,"documentFrequency":1,"idf":0.806179613457731,"absoluteTfIdf":1.612359226915462,"relativeTfIdf":0.0009456652357275438},{"label":"scarce","frequency":1,"documentFrequency":1,"idf":1.598911499447113,"absoluteTfIdf":1.598911499447113,"relativeTfIdf":0.0009377780055408288},{"label":"wit","frequency":1,"documentFrequency":1,"idf":1.5936895554659611,"absoluteTfIdf":1.5936895554659611,"relativeTfIdf":0.0009347152817982177},{"label":"apprehension","frequency":1,"documentFrequency":1,"idf":1.588494738588857,"absoluteTfIdf":1.588494738588857,"relativeTfIdf":0.0009316684683805613},{"label":"title","frequency":1,"documentFrequency":1,"idf":1.5833267684304144,"absoluteTfIdf":1.5833267684304144,"relativeTfIdf":0.0009286374008389527},{"label":"choice","frequency":1,"documentFrequency":1,"idf":1.5781853689299958,"absoluteTfIdf":1.5781853689299958,"relativeTfIdf":0.0009256219172609947},{"label":"deliver","frequency":1,"documentFrequency":1,"idf":1.5730702682632254,"absoluteTfIdf":1.5730702682632254,"relativeTfIdf":0.0009226218582189006},{"label":"property","frequency":1,"documentFrequency":1,"idf":1.5730702682632254,"absoluteTfIdf":1.5730702682632254,"relativeTfIdf":0.0009226218582189006},{"label":"rank","frequency":1,"documentFrequency":1,"idf":1.5730702682632254,"absoluteTfIdf":1.5730702682632254,"relativeTfIdf":0.0009226218582189006},{"label":"one","frequency":4,"documentFrequency":1,"idf":0.39128047311620795,"absoluteTfIdf":1.5651218924648318,"relativeTfIdf":0.0009179600542315729},{"label":"owe","frequency":1,"documentFrequency":1,"idf":1.5528675609457059,"absoluteTfIdf":1.5528675609457059,"relativeTfIdf":0.0009107727630180094},{"label":"take","frequency":3,"documentFrequency":1,"idf":0.5161306759956839,"absoluteTfIdf":1.5483920279870516,"relativeTfIdf":0.0009081478170012032},{"label":"maxim","frequency":1,"documentFrequency":1,"idf":1.547880019434667,"absoluteTfIdf":1.547880019434667,"relativeTfIdf":0.0009078475187300099},{"label":"prejudice","frequency":1,"documentFrequency":1,"idf":1.547880019434667,"absoluteTfIdf":1.547880019434667,"relativeTfIdf":0.0009078475187300099},{"label":"with","frequency":4,"documentFrequency":1,"idf":0.3819346106979702,"absoluteTfIdf":1.5277384427918808,"relativeTfIdf":0.0008960342772972908},{"label":"lord","frequency":1,"documentFrequency":1,"idf":1.5184661342283736,"absoluteTfIdf":1.5184661342283736,"relativeTfIdf":0.0008905959731544713},{"label":"hard","frequency":1,"documentFrequency":1,"idf":1.5136468477924248,"absoluteTfIdf":1.5136468477924248,"relativeTfIdf":0.0008877694121949705},{"label":"pay","frequency":1,"documentFrequency":1,"idf":1.4945986528217303,"absoluteTfIdf":1.4945986528217303,"relativeTfIdf":0.0008765974503353257},{"label":"particularly","frequency":1,"documentFrequency":1,"idf":1.4898927617843176,"absoluteTfIdf":1.4898927617843176,"relativeTfIdf":0.0008738373969409488},{"label":"persuade","frequency":1,"documentFrequency":1,"idf":1.48054689936608,"absoluteTfIdf":1.48054689936608,"relativeTfIdf":0.0008683559527073783},{"label":"company","frequency":1,"documentFrequency":1,"idf":1.4712875739532831,"absoluteTfIdf":1.4712875739532831,"relativeTfIdf":0.0008629252633157086},{"label":"much","frequency":3,"documentFrequency":1,"idf":0.48815682395327775,"absoluteTfIdf":1.4644704718598334,"relativeTfIdf":0.0008589269629676442},{"label":"somewhat","frequency":1,"documentFrequency":1,"idf":1.444013156033624,"absoluteTfIdf":1.444013156033624,"relativeTfIdf":0.0008469285372631226},{"label":"fail","frequency":1,"documentFrequency":1,"idf":1.4350845252893227,"absoluteTfIdf":1.4350845252893227,"relativeTfIdf":0.0008416918036887524},{"label":"understand","frequency":2,"documentFrequency":1,"idf":0.7156200364120039,"absoluteTfIdf":1.4312400728240078,"relativeTfIdf":0.0008394369928586556},{"label":"reflect","frequency":1,"documentFrequency":1,"idf":1.4306499282214569,"absoluteTfIdf":1.4306499282214569,"relativeTfIdf":0.0008390908669920568},{"label":"philosopher","frequency":1,"documentFrequency":1,"idf":1.4262349100123402,"absoluteTfIdf":1.4262349100123402,"relativeTfIdf":0.0008365014134969737},{"label":"give","frequency":3,"documentFrequency":1,"idf":0.4710623905939776,"absoluteTfIdf":1.4131871717819329,"relativeTfIdf":0.0008288487811037729},{"label":"master","frequency":1,"documentFrequency":1,"idf":1.4131056185705473,"absoluteTfIdf":1.4131056185705473,"relativeTfIdf":0.0008288009493082389},{"label":"language","frequency":1,"documentFrequency":1,"idf":1.4087672169719492,"absoluteTfIdf":1.4087672169719492,"relativeTfIdf":0.0008262564322416124},{"label":"possibly","frequency":1,"documentFrequency":1,"idf":1.4087672169719492,"absoluteTfIdf":1.4087672169719492,"relativeTfIdf":0.0008262564322416124},{"label":"only","frequency":3,"documentFrequency":1,"idf":0.4659905284960173,"absoluteTfIdf":1.397971585488052,"relativeTfIdf":0.0008199246835707049},{"label":"use","frequency":2,"documentFrequency":1,"idf":0.6942059419081874,"absoluteTfIdf":1.3884118838163748,"relativeTfIdf":0.0008143178204201612},{"label":"capacity","frequency":1,"documentFrequency":1,"idf":1.3663879940030876,"absoluteTfIdf":1.3663879940030876,"relativeTfIdf":0.0008014005829930133},{"label":"divine","frequency":1,"documentFrequency":1,"idf":1.3622472013370563,"absoluteTfIdf":1.3622472013370563,"relativeTfIdf":0.0007989719655935814},{"label":"whole","frequency":2,"documentFrequency":1,"idf":0.6794843300828275,"absoluteTfIdf":1.358968660165655,"relativeTfIdf":0.0007970490675458387},{"label":"hence","frequency":1,"documentFrequency":1,"idf":1.3581234841531944,"absoluteTfIdf":1.3581234841531944,"relativeTfIdf":0.0007965533631397035},{"label":"justly","frequency":1,"documentFrequency":1,"idf":1.3377561813287606,"absoluteTfIdf":1.3377561813287606,"relativeTfIdf":0.0007846077309846103},{"label":"favour","frequency":1,"documentFrequency":1,"idf":1.3337320310290353,"absoluteTfIdf":1.3337320310290353,"relativeTfIdf":0.0007822475255302259},{"label":"difficult","frequency":1,"documentFrequency":1,"idf":1.3297240096314962,"absoluteTfIdf":1.3297240096314962,"relativeTfIdf":0.0007798967798425197},{"label":"fancy","frequency":1,"documentFrequency":1,"idf":1.3297240096314962,"absoluteTfIdf":1.3297240096314962,"relativeTfIdf":0.0007798967798425197},{"label":"deny","frequency":1,"documentFrequency":1,"idf":1.3099213823353166,"absoluteTfIdf":1.3099213823353166,"relativeTfIdf":0.0007682823356805376},{"label":"distinction","frequency":1,"documentFrequency":1,"idf":1.3060074830141803,"absoluteTfIdf":1.3060074830141803,"relativeTfIdf":0.000765986793556704},{"label":"chief","frequency":1,"documentFrequency":1,"idf":1.302108842598523,"absoluteTfIdf":1.302108842598523,"relativeTfIdf":0.0007637002009375501},{"label":"false","frequency":1,"documentFrequency":1,"idf":1.302108842598523,"absoluteTfIdf":1.302108842598523,"relativeTfIdf":0.0007637002009375501},{"label":"old","frequency":1,"documentFrequency":1,"idf":1.294356865794205,"absoluteTfIdf":1.294356865794205,"relativeTfIdf":0.0007591535869760734},{"label":"heart","frequency":1,"documentFrequency":1,"idf":1.2866645201710494,"absoluteTfIdf":1.2866645201710494,"relativeTfIdf":0.0007546419473143985},{"label":"apply","frequency":1,"documentFrequency":1,"idf":1.2828404237326458,"absoluteTfIdf":1.2828404237326458,"relativeTfIdf":0.0007523990755030181},{"label":"original","frequency":1,"documentFrequency":1,"idf":1.2828404237326458,"absoluteTfIdf":1.2828404237326458,"relativeTfIdf":0.0007523990755030181},{"label":"notwithstanding","frequency":1,"documentFrequency":1,"idf":1.2639362690934932,"absoluteTfIdf":1.2639362690934932,"relativeTfIdf":0.0007413115947762424},{"label":"example","frequency":1,"documentFrequency":1,"idf":1.252762968495368,"absoluteTfIdf":1.252762968495368,"relativeTfIdf":0.000734758339293471},{"label":"now","frequency":2,"documentFrequency":1,"idf":0.6246482582062772,"absoluteTfIdf":1.2492965164125545,"relativeTfIdf":0.0007327252295674806},{"label":"sort","frequency":1,"documentFrequency":1,"idf":1.2344138298271714,"absoluteTfIdf":1.2344138298271714,"relativeTfIdf":0.0007239963811303058},{"label":"belong","frequency":1,"documentFrequency":1,"idf":1.2271674213064043,"absoluteTfIdf":1.2271674213064043,"relativeTfIdf":0.0007197462881562489},{"label":"bad","frequency":1,"documentFrequency":1,"idf":1.2199731456723772,"absoluteTfIdf":1.2199731456723772,"relativeTfIdf":0.0007155267716553532},{"label":"call","frequency":2,"documentFrequency":1,"idf":0.6089616620385776,"absoluteTfIdf":1.2179233240771552,"relativeTfIdf":0.0007143245302505309},{"label":"oblige","frequency":1,"documentFrequency":1,"idf":1.2057380298505052,"absoluteTfIdf":1.2057380298505052,"relativeTfIdf":0.0007071777301175983},{"label":"foundation","frequency":1,"documentFrequency":1,"idf":1.1986957472250923,"absoluteTfIdf":1.1986957472250923,"relativeTfIdf":0.0007030473590763004},{"label":"friend","frequency":1,"documentFrequency":1,"idf":1.1951931166738903,"absoluteTfIdf":1.1951931166738903,"relativeTfIdf":0.000700993030307267},{"label":"liberty","frequency":1,"documentFrequency":1,"idf":1.1951931166738903,"absoluteTfIdf":1.1951931166738903,"relativeTfIdf":0.000700993030307267},{"label":"nation","frequency":1,"documentFrequency":1,"idf":1.181304004513223,"absoluteTfIdf":1.181304004513223,"relativeTfIdf":0.000692846923468166},{"label":"creature","frequency":1,"documentFrequency":1,"idf":1.174431125225461,"absoluteTfIdf":1.174431125225461,"relativeTfIdf":0.0006888159092231442},{"label":"place","frequency":2,"documentFrequency":1,"idf":0.585883714756033,"absoluteTfIdf":1.171767429512066,"relativeTfIdf":0.0006872536243472527},{"label":"species","frequency":1,"documentFrequency":1,"idf":1.1676051601550612,"absoluteTfIdf":1.1676051601550612,"relativeTfIdf":0.0006848124106481298},{"label":"fit","frequency":1,"documentFrequency":1,"idf":1.1642095711539229,"absoluteTfIdf":1.1642095711539229,"relativeTfIdf":0.0006828208628468755},{"label":"plain","frequency":1,"documentFrequency":1,"idf":1.1642095711539229,"absoluteTfIdf":1.1642095711539229,"relativeTfIdf":0.0006828208628468755},{"label":"something","frequency":1,"documentFrequency":1,"idf":1.1642095711539229,"absoluteTfIdf":1.1642095711539229,"relativeTfIdf":0.0006828208628468755},{"label":"equal","frequency":1,"documentFrequency":1,"idf":1.1474024528375417,"absoluteTfIdf":1.1474024528375417,"relativeTfIdf":0.0006729633154472386},{"label":"necessity","frequency":1,"documentFrequency":1,"idf":1.1308731508863312,"absoluteTfIdf":1.1308731508863312,"relativeTfIdf":0.0006632687101972617},{"label":"religion","frequency":1,"documentFrequency":1,"idf":1.1308731508863312,"absoluteTfIdf":1.1308731508863312,"relativeTfIdf":0.0006632687101972617},{"label":"but","frequency":3,"documentFrequency":1,"idf":0.37421256460405994,"absoluteTfIdf":1.1226376938121798,"relativeTfIdf":0.0006584385300951202},{"label":"relation","frequency":1,"documentFrequency":1,"idf":1.114612630014551,"absoluteTfIdf":1.114612630014551,"relativeTfIdf":0.0006537317478091208},{"label":"know","frequency":2,"documentFrequency":1,"idf":0.5522356806378002,"absoluteTfIdf":1.1044713612756003,"relativeTfIdf":0.0006477837896044576},{"label":"less","frequency":2,"documentFrequency":1,"idf":0.5522356806378002,"absoluteTfIdf":1.1044713612756003,"relativeTfIdf":0.0006477837896044576},{"label":"say","frequency":2,"documentFrequency":1,"idf":0.5503991328304987,"absoluteTfIdf":1.1007982656609974,"relativeTfIdf":0.0006456294813260981},{"label":"full","frequency":1,"documentFrequency":1,"idf":1.092283153616462,"absoluteTfIdf":1.092283153616462,"relativeTfIdf":0.0006406352807134675},{"label":"stand","frequency":1,"documentFrequency":1,"idf":1.092283153616462,"absoluteTfIdf":1.092283153616462,"relativeTfIdf":0.0006406352807134675},{"label":"change","frequency":1,"documentFrequency":1,"idf":1.089133544713566,"absoluteTfIdf":1.089133544713566,"relativeTfIdf":0.0006387880027645548},{"label":"really","frequency":1,"documentFrequency":1,"idf":1.0828639316999706,"absoluteTfIdf":1.0828639316999706,"relativeTfIdf":0.0006351108103812144},{"label":"lead","frequency":1,"documentFrequency":1,"idf":1.0766333819493346,"absoluteTfIdf":1.0766333819493346,"relativeTfIdf":0.0006314565290025423},{"label":"raise","frequency":1,"documentFrequency":1,"idf":1.0735326042710862,"absoluteTfIdf":1.0735326042710862,"relativeTfIdf":0.0006296378910680858},{"label":"evident","frequency":1,"documentFrequency":1,"idf":1.0642875461270351,"absoluteTfIdf":1.0642875461270351,"relativeTfIdf":0.0006242155695759736},{"label":"again","frequency":1,"documentFrequency":1,"idf":1.0612247565964894,"absoluteTfIdf":1.0612247565964894,"relativeTfIdf":0.0006224192120800524},{"label":"small","frequency":1,"documentFrequency":1,"idf":1.058171319109599,"absoluteTfIdf":1.058171319109599,"relativeTfIdf":0.0006206283396537237},{"label":"feel","frequency":1,"documentFrequency":1,"idf":1.052092273033217,"absoluteTfIdf":1.052092273033217,"relativeTfIdf":0.0006170629167350246},{"label":"look","frequency":1,"documentFrequency":1,"idf":1.052092273033217,"absoluteTfIdf":1.052092273033217,"relativeTfIdf":0.0006170629167350246},{"label":"rule","frequency":1,"documentFrequency":1,"idf":1.043042437513299,"absoluteTfIdf":1.043042437513299,"relativeTfIdf":0.0006117550953157178},{"label":"determine","frequency":1,"documentFrequency":1,"idf":0.9989824477192685,"absoluteTfIdf":0.9989824477192685,"relativeTfIdf":0.0005859134590728847},{"label":"bear","frequency":1,"documentFrequency":1,"idf":0.9875537518956456,"absoluteTfIdf":0.9875537518956456,"relativeTfIdf":0.0005792104116690004},{"label":"question","frequency":1,"documentFrequency":1,"idf":0.9875537518956456,"absoluteTfIdf":0.9875537518956456,"relativeTfIdf":0.0005792104116690004},{"label":"every","frequency":2,"documentFrequency":1,"idf":0.49334266098564317,"absoluteTfIdf":0.9866853219712863,"relativeTfIdf":0.00057870106860486},{"label":"very","frequency":2,"documentFrequency":1,"idf":0.49334266098564317,"absoluteTfIdf":0.9866853219712863,"relativeTfIdf":0.00057870106860486},{"label":"ought","frequency":1,"documentFrequency":1,"idf":0.9847168705604459,"absoluteTfIdf":0.9847168705604459,"relativeTfIdf":0.0005775465516483553},{"label":"latter","frequency":1,"documentFrequency":1,"idf":0.9790671380183269,"absoluteTfIdf":0.9790671380183269,"relativeTfIdf":0.0005742329255239454},{"label":"draw","frequency":1,"documentFrequency":1,"idf":0.9678625390054638,"absoluteTfIdf":0.9678625390054638,"relativeTfIdf":0.0005676613131996855},{"label":"respect","frequency":1,"documentFrequency":1,"idf":0.9678625390054638,"absoluteTfIdf":0.9678625390054638,"relativeTfIdf":0.0005676613131996855},{"label":"commonly","frequency":1,"documentFrequency":1,"idf":0.965080896043587,"absoluteTfIdf":0.965080896043587,"relativeTfIdf":0.0005660298510519572},{"label":"thing","frequency":2,"documentFrequency":1,"idf":0.4812839446655157,"absoluteTfIdf":0.9625678893310314,"relativeTfIdf":0.0005645559468217193},{"label":"into","frequency":2,"documentFrequency":1,"idf":0.4761601076656463,"absoluteTfIdf":0.9523202153312926,"relativeTfIdf":0.0005585455808394678},{"label":"live","frequency":1,"documentFrequency":1,"idf":0.9512875739112513,"absoluteTfIdf":0.9512875739112513,"relativeTfIdf":0.0005579399260476547},{"label":"reason","frequency":2,"documentFrequency":1,"idf":0.4693689100876446,"absoluteTfIdf":0.9387378201752892,"relativeTfIdf":0.0005505793666717238},{"label":"human","frequency":1,"documentFrequency":1,"idf":0.9349828648863077,"absoluteTfIdf":0.9349828648863077,"relativeTfIdf":0.0005483770468541393},{"label":"imagine","frequency":1,"documentFrequency":1,"idf":0.9296065078499273,"absoluteTfIdf":0.9296065078499273,"relativeTfIdf":0.0005452237582697521},{"label":"sufficient","frequency":1,"documentFrequency":1,"idf":0.9296065078499273,"absoluteTfIdf":0.9296065078499273,"relativeTfIdf":0.0005452237582697521},{"label":"instance","frequency":1,"documentFrequency":1,"idf":0.9269291300792109,"absoluteTfIdf":0.9269291300792109,"relativeTfIdf":0.0005436534487268099},{"label":"i","frequency":2,"documentFrequency":1,"idf":0.4592678141011407,"absoluteTfIdf":0.9185356282022814,"relativeTfIdf":0.0005387305737256783},{"label":"bring","frequency":1,"documentFrequency":1,"idf":0.9031499383130968,"absoluteTfIdf":0.9031499383130968,"relativeTfIdf":0.0005297067086880333},{"label":"put","frequency":1,"documentFrequency":1,"idf":0.8953475580289119,"absoluteTfIdf":0.8953475580289119,"relativeTfIdf":0.0005251305325682768},{"label":"go","frequency":1,"documentFrequency":1,"idf":0.8773753156244816,"absoluteTfIdf":0.8773753156244816,"relativeTfIdf":0.0005145896279322473},{"label":"rather","frequency":1,"documentFrequency":1,"idf":0.8773753156244816,"absoluteTfIdf":0.8773753156244816,"relativeTfIdf":0.0005145896279322473},{"label":"hand","frequency":1,"documentFrequency":1,"idf":0.8547328388747217,"absoluteTfIdf":0.8547328388747217,"relativeTfIdf":0.0005013095829177254},{"label":"end","frequency":1,"documentFrequency":1,"idf":0.8374697714509409,"absoluteTfIdf":0.8374697714509409,"relativeTfIdf":0.0004911846166867689},{"label":"regard","frequency":1,"documentFrequency":1,"idf":0.8325917129975081,"absoluteTfIdf":0.8325917129975081,"relativeTfIdf":0.0004883235853357818},{"label":"allow","frequency":1,"documentFrequency":1,"idf":0.82773733453271,"absoluteTfIdf":0.82773733453271,"relativeTfIdf":0.0004854764425411789},{"label":"opinion","frequency":1,"documentFrequency":1,"idf":0.8229064072630444,"absoluteTfIdf":0.8229064072630444,"relativeTfIdf":0.0004826430541132225},{"label":"pleasure","frequency":1,"documentFrequency":1,"idf":0.8157034949689864,"absoluteTfIdf":0.8157034949689864,"relativeTfIdf":0.0004784184721225727},{"label":"account","frequency":1,"documentFrequency":1,"idf":0.8133140075716051,"absoluteTfIdf":0.8133140075716051,"relativeTfIdf":0.00047701701323847807},{"label":"indeed","frequency":1,"documentFrequency":1,"idf":0.8014514722617849,"absoluteTfIdf":0.8014514722617849,"relativeTfIdf":0.00047005951452304103},{"label":"principle","frequency":1,"documentFrequency":1,"idf":0.7944009142651182,"absoluteTfIdf":0.7944009142651182,"relativeTfIdf":0.0004659242898915649},{"label":"up","frequency":1,"documentFrequency":1,"idf":0.7758388964050588,"absoluteTfIdf":0.7758388964050588,"relativeTfIdf":0.00045503747589739515},{"label":"life","frequency":1,"documentFrequency":1,"idf":0.7712517323981525,"absoluteTfIdf":0.7712517323981525,"relativeTfIdf":0.0004523470571250161},{"label":"accord","frequency":1,"documentFrequency":1,"idf":0.7644102005814359,"absoluteTfIdf":0.7644102005814359,"relativeTfIdf":0.0004483344284935108},{"label":"long","frequency":1,"documentFrequency":1,"idf":0.7621400520468967,"absoluteTfIdf":0.7621400520468967,"relativeTfIdf":0.0004470029630773588},{"label":"come","frequency":1,"documentFrequency":1,"idf":0.7531106453275026,"absoluteTfIdf":0.7531106453275026,"relativeTfIdf":0.00044170712335923906},{"label":"whether","frequency":1,"documentFrequency":1,"idf":0.7486263328801739,"absoluteTfIdf":0.7486263328801739,"relativeTfIdf":0.00043907702808221343},{"label":"occasion","frequency":1,"documentFrequency":1,"idf":0.7441620397514884,"absoluteTfIdf":0.7441620397514884,"relativeTfIdf":0.0004364586743410489},{"label":"often","frequency":1,"documentFrequency":1,"idf":0.7419373447293773,"absoluteTfIdf":0.7419373447293773,"relativeTfIdf":0.00043515386787646766},{"label":"perhaps","frequency":1,"documentFrequency":1,"idf":0.7352928020107088,"absoluteTfIdf":0.7352928020107088,"relativeTfIdf":0.0004312567753728497},{"label":"different","frequency":1,"documentFrequency":1,"idf":0.7330877294523948,"absoluteTfIdf":0.7330877294523948,"relativeTfIdf":0.000429963477684689},{"label":"general","frequency":1,"documentFrequency":1,"idf":0.7308875085427924,"absoluteTfIdf":0.7308875085427924,"relativeTfIdf":0.00042867302553829464},{"label":"out","frequency":1,"documentFrequency":1,"idf":0.7156200364120039,"absoluteTfIdf":0.7156200364120039,"relativeTfIdf":0.0004197184964293278},{"label":"world","frequency":1,"documentFrequency":1,"idf":0.7156200364120039,"absoluteTfIdf":0.7156200364120039,"relativeTfIdf":0.0004197184964293278},{"label":"order","frequency":1,"documentFrequency":1,"idf":0.7134578734075088,"absoluteTfIdf":0.7134578734075088,"relativeTfIdf":0.0004184503656349025},{"label":"object","frequency":1,"documentFrequency":1,"idf":0.7091475219063864,"absoluteTfIdf":0.7091475219063864,"relativeTfIdf":0.0004159223002383498},{"label":"true","frequency":1,"documentFrequency":1,"idf":0.7005821590474633,"absoluteTfIdf":0.7005821590474633,"relativeTfIdf":0.0004108986270073099},{"label":"little","frequency":1,"documentFrequency":1,"idf":0.6773988235918061,"absoluteTfIdf":0.6773988235918061,"relativeTfIdf":0.0003973013628104435},{"label":"after","frequency":1,"documentFrequency":1,"idf":0.6670360365562595,"absoluteTfIdf":0.6670360365562595,"relativeTfIdf":0.0003912234818511786},{"label":"because","frequency":1,"documentFrequency":1,"idf":0.664976303593249,"absoluteTfIdf":0.664976303593249,"relativeTfIdf":0.00039001542732741874},{"label":"subject","frequency":1,"documentFrequency":1,"idf":0.6486494103058202,"absoluteTfIdf":0.6486494103058202,"relativeTfIdf":0.0003804395368362582},{"label":"two","frequency":1,"documentFrequency":1,"idf":0.6466271649250525,"absoluteTfIdf":0.6466271649250525,"relativeTfIdf":0.00037925346916425364},{"label":"way","frequency":1,"documentFrequency":1,"idf":0.634578826408878,"absoluteTfIdf":0.634578826408878,"relativeTfIdf":0.00037218699496121876},{"label":"observe","frequency":1,"documentFrequency":1,"idf":0.626626498218383,"absoluteTfIdf":0.626626498218383,"relativeTfIdf":0.0003675228728553566},{"label":"mean","frequency":1,"documentFrequency":1,"idf":0.5801964956354433,"absoluteTfIdf":0.5801964956354433,"relativeTfIdf":0.00034029119978618374},{"label":"time","frequency":1,"documentFrequency":1,"idf":0.5467361250717615,"absoluteTfIdf":0.5467361250717615,"relativeTfIdf":0.0003206663490156959},{"label":"therefore","frequency":1,"documentFrequency":1,"idf":0.5214640219710465,"absoluteTfIdf":0.5214640219710465,"relativeTfIdf":0.00030584400115603896},{"label":"nor","frequency":1,"documentFrequency":1,"idf":0.5161306759956839,"absoluteTfIdf":0.5161306759956839,"relativeTfIdf":0.0003027159390004011},{"label":"first","frequency":1,"documentFrequency":1,"idf":0.5143591963473018,"absoluteTfIdf":0.5143591963473018,"relativeTfIdf":0.00030167694800428257},{"label":"part","frequency":1,"documentFrequency":1,"idf":0.5020459361139449,"absoluteTfIdf":0.5020459361139449,"relativeTfIdf":0.0002944550944949823},{"label":"yet","frequency":1,"documentFrequency":1,"idf":0.5002992107790032,"absoluteTfIdf":0.5002992107790032,"relativeTfIdf":0.0002934306221577731},{"label":"find","frequency":1,"documentFrequency":1,"idf":0.4744579795951159,"absoluteTfIdf":0.4744579795951159,"relativeTfIdf":0.0002782744748358451},{"label":"though","frequency":1,"documentFrequency":1,"idf":0.4592678141011407,"absoluteTfIdf":0.4592678141011407,"relativeTfIdf":0.0002693652868628391},{"label":"shall","frequency":1,"documentFrequency":1,"idf":0.4230796548091466,"absoluteTfIdf":0.4230796548091466,"relativeTfIdf":0.00024814056000536456}],"numbers":["1","1","105","13","15","16","298","3","306","310"],"names":[],"foreignText":[" Haud illud quaerentes, num sine SENSU,   Tempore num faciant alieno.  ,","Haec nostri pars optima Senss.","Haec satis ad Juvenem, quem nobis fama superbum   Tradit, & inflatum, plenumque Nerone propinquo.","Justitiae partes sunt, non violare homines: Verecundiae, non offendere.","Odium autem ex offensa sic vitabis, neminem lacessendo gratuit:  quo te SENSUS COMMUNIS tuebitur.","Rarus enim ferm Sensus communis in ill   Fortun ","SENSUS","Subjicit ver Antoninus quasi hanc vocem interpretans,         ,   .","moderatam, usitatam & ordinariam hominis mentem quae in commune quodammodo consulit, nec omnia ad commodum suum refert, respectumque etiam habet eorum cum quibus versatur, modest, modicque de se sentiens. At contra inflati & superbi omnes se sibi tantm suisque commodis natos arbitrantur, & prae se caeteros contemnunt & negligunt; & hi sunt qui Sensum Communem non habere rect dici possunt. Nam ita Sensum Communem accipit Juvenalis, Sat. 8. Rarus enim ferm SENSUS COMMUNIS, &c.  &  Galenus vocat, quam Marcus de se loquens ; & alibi, ubi de eadem re loquitur,   , qua gratiam illi fecerit Marcus simul eundi ad Germanicum Bellum ac sequendi se.","","","","","","","",""," ","   ",""],"citations":["Juv. Sat. 8.","Juv. Sat. 8. v. 73.","Lib. 1. de Off.","Sat. 4. v. 77."],"marginComments":[]}